Workbook

Sheet Employee Master Table
A1: Employee ID | B1: Employee Name | C1: Signature | D1: Department | E1: Designation | F1: Date of Joining | G1: Bank Name | H1: Bank Account No. | I1: PAN | J1: PF Applicable | K1: ESI Applicable | L1: Status | P1: 46023
A2: EMP001 | B2: Aarav Sharma | C2: Aarav Sharma | D2: Engineering | E2: Software Engineer | F2: 45306 | G2: HDFC Bank | H2: 50100234561001 | I2: AAAAA1237A | J2: Yes | K2: Yes | L2: Active | P2: 46054
A3: EMP002 | B3: Riya Verma | C3: Riya Verma | D3: HR | E3: HR Executive | F3: 45361 | G3: ICICI Bank | H3: 00340123456702 | I3: BBBBB2345B | J3: Yes | K3: Yes | L3: Active | P3: 46082
A4: EMP003 | B4: Kunal Jain | C4: Kunal Jain | D4: Finance | E4: Accountant | F4: 45112 | G4: SBI | H4: 31245678903001 | I4: CCCCC3456C | J4: Yes | K4: Yes | L4: Active | P4: 46113
A5: EMP004 | B5: Ananya Singh | C5: Ananya Singh | D5: Marketing | E5: Marketing Executive | F5: 45708 | G5: Axis Bank | H5: 91201004567804 | I5: DDDDD0456D | J5: Yes | K5: Yes | L5: Active | P5: 46143
A6: EMP005 | B6: Rahul Mehta | C6: Rahul Mehta | D6: Engineering | E6: Data Analyst | F6: 45516 | G6: HDFC Bank | H6: 50100234561005 | I6: EEEEE5678E | J6: Yes | K6: Yes | L6: Active | P6: 46174
A7: EMP006 | B7: Priya Patel | C7: Priya Patel | D7: Operations | E7: Operations Executive | F7: 45187 | G7: SBI | H7: 31245678906006 | I7: FFFFF6789F | J7: Yes | K7: Yes | L7: Active | P7: 46204
A8: EMP007 | B8: Aditya Gupta | C8: Aditya Gupta | D8: Engineering | E8: ML Engineer | F8: 45659 | G8: ICICI Bank | H8: 00340123456707 | I8: GGGGG7098G | J8: Yes | K8: Yes | L8: Active | P8: 46235
A9: EMP008 | B9: Sneha Joshi | C9: Sneha Joshi | D9: Finance | E9: Financial Analyst | F9: 45407 | G9: Axis Bank | H9: 91201004567808 | I9: HHHHH8901H | J9: Yes | K9: Yes | L9: Active | P9: 46266
A10: EMP009 | B10: Mohit Verma | C10: Mohit Verma | D10: Sales | E10: Sales Executive | F10: 45454 | G10: HDFC Bank | H10: 50100234561009 | I10: JJJJJ9012J | J10: Yes | K10: Yes | L10: Active | P10: 46296
A11: EMP010 | B11: Neha Kapoor | C11: Neha Kapoor | D11: HR | E11: HR Manager | F11: 44873 | G11: SBI | H11: 31245678900010 | I11: KKKKK0123K | J11: Yes | K11: Yes | L11: Active | P11: 46327
P12: 46357

Sheet Salary Structure
A1: Employee ID | B1: Basic Salary | C1: HRA | D1: Conveyance | E1: Special Allowance
A2: ='Employee Master Table'!A2 -> EMP001 | B2: 30000 | C2: =B2*40/100 -> 12000 | D2: =B2*10/100 -> 3000 | E2: 5000
A3: ='Employee Master Table'!A3 -> EMP002 | B3: 25000 | C3: =B3*40/100 -> 10000 | D3: =B3*10/100 -> 2500 | E3: 4000
A4: ='Employee Master Table'!A4 -> EMP003 | B4: 28000 | C4: =B4*40/100 -> 11200 | D4: =B4*10/100 -> 2800 | E4: 4500
A5: ='Employee Master Table'!A5 -> EMP004 | B5: 26000 | C5: =B5*40/100 -> 10400 | D5: =B5*10/100 -> 2600 | E5: 4000
A6: ='Employee Master Table'!A6 -> EMP005 | B6: 32000 | C6: =B6*40/100 -> 12800 | D6: =B6*10/100 -> 3200 | E6: 5500
A7: ='Employee Master Table'!A7 -> EMP006 | B7: 24000 | C7: =B7*40/100 -> 9600 | D7: =B7*10/100 -> 2400 | E7: 3500
A8: ='Employee Master Table'!A8 -> EMP007 | B8: 40000 | C8: =B8*40/100 -> 16000 | D8: =B8*10/100 -> 4000 | E8: 7000
A9: ='Employee Master Table'!A9 -> EMP008 | B9: 30000 | C9: =B9*40/100 -> 12000 | D9: =B9*10/100 -> 3000 | E9: 5000
A10: ='Employee Master Table'!A10 -> EMP009 | B10: 23000 | C10: =B10*40/100 -> 9200 | D10: =B10*10/100 -> 2300 | E10: 3500
A11: ='Employee Master Table'!A11 -> EMP010 | B11: 45000 | C11: =B11*40/100 -> 18000 | D11: =B11*10/100 -> 4500 | E11: 8000

Sheet Employee data
A1: Employee ID | B1: Salary Month | C1: Working Days | D1: LOP Days | E1: Paid Days | F1: Basic Salary | G1: House Rent Allowance | H1: Conveyance Allowance | I1: Special Allowance | J1: Other Earnings | K1: Payable Basic | L1: Gross Earnings | M1: Provident Fund (PF) | N1: ESI | O1: Professional Tax | P1: TDS | Q1: Other Deductions | R1: Other Deduction Remark | S1: Total Deductions | T1: Net Salary
A2: EMP001 | B2: 46023 | C2: =DAY(EOMONTH(B2,0)) -> 31 | D2: 1 | E2: =C2-D2 -> 30 | F2: =_xlfn.XLOOKUP(A2,'Salary Structure'!A:A,'Salary Structure'!B:B,"NOT FOUND") -> 30000 | G2: =_xlfn.XLOOKUP(A2,'Salary Structure'!A:A,'Salary Structure'!C:C,"NOT FOUND")*E2/C2 -> 11612.903 | H2: =_xlfn.XLOOKUP(A2,'Salary Structure'!A:A,'Salary Structure'!D:D,"NOT FOUND")*E2/C2 -> 2903.2258 | I2: =_xlfn.XLOOKUP(A2,'Salary Structure'!A:A,'Salary Structure'!E:E,"NOT FOUND")*E2/C2 -> 4838.7097 | J2: 0 | K2: =ROUND(F2*E2/C2,0) -> 29032 | L2: =SUM(G2:K2) -> 48386.839 | M2: =F2*12/100 -> 3600 | N2: =L2*75/10000 -> 362.90129 | O2: 208 | P2: =L2*3/100 -> 1451.6052 | Q2: 0 | S2: =M2+N2+O2+P2+Q2 -> 5622.5065 | T2: =L2-S2 -> 42764.332
A3: EMP002 | B3: 46023 | C3: =DAY(EOMONTH(B3,0)) -> 31 | D3: 2 | E3: =C3-D3 -> 29 | F3: =_xlfn.XLOOKUP(A3,'Salary Structure'!A:A,'Salary Structure'!B:B,"NOT FOUND") -> 25000 | G3: =_xlfn.XLOOKUP(A3,'Salary Structure'!A:A,'Salary Structure'!C:C,"NOT FOUND")*E3/C3 -> 9354.8387 | H3: =_xlfn.XLOOKUP(A3,'Salary Structure'!A:A,'Salary Structure'!D:D,"NOT FOUND")*E3/C3 -> 2338.7097 | I3: =_xlfn.XLOOKUP(A3,'Salary Structure'!A:A,'Salary Structure'!E:E,"NOT FOUND")*E3/C3 -> 3741.9355 | J3: 0 | K3: =ROUND(F3*E3/C3,0) -> 23387 | L3: =SUM(G3:K3) -> 38822.484 | M3: =F3*12/100 -> 3000 | N3: =L3*75/10000 -> 291.16863 | O3: 208 | P3: =L3*3/100 -> 1164.6745 | Q3: 0 | S3: =M3+N3+O3+P3+Q3 -> 4663.8431 | T3: =L3-S3 -> 34158.641
A4: EMP003 | B4: 46023 | C4: =DAY(EOMONTH(B4,0)) -> 31 | D4: 1 | E4: =C4-D4 -> 30 | F4: =_xlfn.XLOOKUP(A4,'Salary Structure'!A:A,'Salary Structure'!B:B,"NOT FOUND") -> 28000 | G4: =_xlfn.XLOOKUP(A4,'Salary Structure'!A:A,'Salary Structure'!C:C,"NOT FOUND")*E4/C4 -> 10838.71 | H4: =_xlfn.XLOOKUP(A4,'Salary Structure'!A:A,'Salary Structure'!D:D,"NOT FOUND")*E4/C4 -> 2709.6774 | I4: =_xlfn.XLOOKUP(A4,'Salary Structure'!A:A,'Salary Structure'!E:E,"NOT FOUND")*E4/C4 -> 4354.8387 | J4: 0 | K4: =ROUND(F4*E4/C4,0) -> 27097 | L4: =SUM(G4:K4) -> 45000.226 | M4: =F4*12/100 -> 3360 | N4: =L4*75/10000 -> 337.50169 | O4: 208 | P4: =L4*3/100 -> 1350.0068 | Q4: 300 | R4: Loan/Advance EMI recovery | S4: =M4+N4+O4+P4+Q4 -> 5555.5085 | T4: =L4-S4 -> 39444.717
A5: EMP004 | B5: 46023 | C5: =DAY(EOMONTH(B5,0)) -> 31 | D5: 0 | E5: =C5-D5 -> 31 | F5: =_xlfn.XLOOKUP(A5,'Salary Structure'!A:A,'Salary Structure'!B:B,"NOT FOUND") -> 26000 | G5: =_xlfn.XLOOKUP(A5,'Salary Structure'!A:A,'Salary Structure'!C:C,"NOT FOUND")*E5/C5 -> 10400 | H5: =_xlfn.XLOOKUP(A5,'Salary Structure'!A:A,'Salary Structure'!D:D,"NOT FOUND")*E5/C5 -> 2600 | I5: =_xlfn.XLOOKUP(A5,'Salary Structure'!A:A,'Salary Structure'!E:E,"NOT FOUND")*E5/C5 -> 4000 | J5: 0 | K5: =ROUND(F5*E5/C5,0) -> 26000 | L5: =SUM(G5:K5) -> 43000 | M5: =F5*12/100 -> 3120 | N5: =L5*75/10000 -> 322.5 | O5: 208 | P5: =L5*3/100 -> 1290 | Q5: 0 | S5: =M5+N5+O5+P5+Q5 -> 4940.5 | T5: =L5-S5 -> 38059.5
A6: EMP005 | B6: 46023 | C6: =DAY(EOMONTH(B6,0)) -> 31 | D6: 2 | E6: =C6-D6 -> 29 | F6: =_xlfn.XLOOKUP(A6,'Salary Structure'!A:A,'Salary Structure'!B:B,"NOT FOUND") -> 32000 | G6: =_xlfn.XLOOKUP(A6,'Salary Structure'!A:A,'Salary Structure'!C:C,"NOT FOUND")*E6/C6 -> 11974.194 | H6: =_xlfn.XLOOKUP(A6,'Salary Structure'!A:A,'Salary Structure'!D:D,"NOT FOUND")*E6/C6 -> 2993.5484 | I6: =_xlfn.XLOOKUP(A6,'Salary Structure'!A:A,'Salary Structure'!E:E,"NOT FOUND")*E6/C6 -> 5145.1613 | J6: 0 | K6: =ROUND(F6*E6/C6,0) -> 29935 | L6: =SUM(G6:K6) -> 50047.903 | M6: =F6*12/100 -> 3840 | N6: =L6*75/10000 -> 375.35927 | O6: 208 | P6: =L6*3/100 -> 1501.4371 | Q6: 0 | S6: =M6+N6+O6+P6+Q6 -> 5924.7964 | T6: =L6-S6 -> 44123.107
A7: EMP006 | B7: 46023 | C7: =DAY(EOMONTH(B7,0)) -> 31 | D7: 1 | E7: =C7-D7 -> 30 | F7: =_xlfn.XLOOKUP(A7,'Salary Structure'!A:A,'Salary Structure'!B:B,"NOT FOUND") -> 24000 | G7: =_xlfn.XLOOKUP(A7,'Salary Structure'!A:A,'Salary Structure'!C:C,"NOT FOUND")*E7/C7 -> 9290.3226 | H7: =_xlfn.XLOOKUP(A7,'Salary Structure'!A:A,'Salary Structure'!D:D,"NOT FOUND")*E7/C7 -> 2322.5806 | I7: =_xlfn.XLOOKUP(A7,'Salary Structure'!A:A,'Salary Structure'!E:E,"NOT FOUND")*E7/C7 -> 3387.0968 | J7: 0 | K7: =ROUND(F7*E7/C7,0) -> 23226 | L7: =SUM(G7:K7) -> 38226 | M7: =F7*12/100 -> 2880 | N7: =L7*75/10000 -> 286.695 | O7: 208 | P7: =L7*3/100 -> 1146.78 | Q7: 0 | S7: =M7+N7+O7+P7+Q7 -> 4521.475 | T7: =L7-S7 -> 33704.525
A8: EMP007 | B8: 46023 | C8: =DAY(EOMONTH(B8,0)) -> 31 | D8: 2 | E8: =C8-D8 -> 29 | F8: =_xlfn.XLOOKUP(A8,'Salary Structure'!A:A,'Salary Structure'!B:B,"NOT FOUND") -> 40000 | G8: =_xlfn.XLOOKUP(A8,'Salary Structure'!A:A,'Salary Structure'!C:C,"NOT FOUND")*E8/C8 -> 14967.742 | H8: =_xlfn.XLOOKUP(A8,'Salary Structure'!A:A,'Salary Structure'!D:D,"NOT FOUND")*E8/C8 -> 3741.9355 | I8: =_xlfn.XLOOKUP(A8,'Salary Structure'!A:A,'Salary Structure'!E:E,"NOT FOUND")*E8/C8 -> 6548.3871 | J8: 0 | K8: =ROUND(F8*E8/C8,0) -> 37419 | L8: =SUM(G8:K8) -> 62677.065 | M8: =F8*12/100 -> 4800 | N8: =L8*75/10000 -> 470.07798 | O8: 208 | P8: =L8*3/100 -> 1880.3119 | Q8: 0 | S8: =M8+N8+O8+P8+Q8 -> 7358.3899 | T8: =L8-S8 -> 55318.675
A9: EMP008 | B9: 46023 | C9: =DAY(EOMONTH(B9,0)) -> 31 | D9: 0 | E9: =C9-D9 -> 31 | F9: =_xlfn.XLOOKUP(A9,'Salary Structure'!A:A,'Salary Structure'!B:B,"NOT FOUND") -> 30000 | G9: =_xlfn.XLOOKUP(A9,'Salary Structure'!A:A,'Salary Structure'!C:C,"NOT FOUND")*E9/C9 -> 12000 | H9: =_xlfn.XLOOKUP(A9,'Salary Structure'!A:A,'Salary Structure'!D:D,"NOT FOUND")*E9/C9 -> 3000 | I9: =_xlfn.XLOOKUP(A9,'Salary Structure'!A:A,'Salary Structure'!E:E,"NOT FOUND")*E9/C9 -> 5000 | J9: 0 | K9: =ROUND(F9*E9/C9,0) -> 30000 | L9: =SUM(G9:K9) -> 50000 | M9: =F9*12/100 -> 3600 | N9: =L9*75/10000 -> 375 | O9: 208 | P9: =L9*3/100 -> 1500 | Q9: 0 | S9: =M9+N9+O9+P9+Q9 -> 5683 | T9: =L9-S9 -> 44317
A10: EMP009 | B10: 46023 | C10: =DAY(EOMONTH(B10,0)) -> 31 | D10: 7 | E10: =C10-D10 -> 24 | F10: =_xlfn.XLOOKUP(A10,'Salary Structure'!A:A,'Salary Structure'!B:B,"NOT FOUND") -> 23000 | G10: =_xlfn.XLOOKUP(A10,'Salary Structure'!A:A,'Salary Structure'!C:C,"NOT FOUND")*E10/C10 -> 7122.5806 | H10: =_xlfn.XLOOKUP(A10,'Salary Structure'!A:A,'Salary Structure'!D:D,"NOT FOUND")*E10/C10 -> 1780.6452 | I10: =_xlfn.XLOOKUP(A10,'Salary Structure'!A:A,'Salary Structure'!E:E,"NOT FOUND")*E10/C10 -> 2709.6774 | J10: 0 | K10: =ROUND(F10*E10/C10,0) -> 17806 | L10: =SUM(G10:K10) -> 29418.903 | M10: =F10*12/100 -> 2760 | N10: =L10*75/10000 -> 220.64177 | O10: 167 | P10: =L10*3/100 -> 882.5671 | Q10: 0 | S10: =M10+N10+O10+P10+Q10 -> 4030.2089 | T10: =L10-S10 -> 25388.694
A11: EMP010 | B11: 46023 | C11: =DAY(EOMONTH(B11,0)) -> 31 | D11: 0 | E11: =C11-D11 -> 31 | F11: =_xlfn.XLOOKUP(A11,'Salary Structure'!A:A,'Salary Structure'!B:B,"NOT FOUND") -> 45000 | G11: =_xlfn.XLOOKUP(A11,'Salary Structure'!A:A,'Salary Structure'!C:C,"NOT FOUND")*E11/C11 -> 18000 | H11: =_xlfn.XLOOKUP(A11,'Salary Structure'!A:A,'Salary Structure'!D:D,"NOT FOUND")*E11/C11 -> 4500 | I11: =_xlfn.XLOOKUP(A11,'Salary Structure'!A:A,'Salary Structure'!E:E,"NOT FOUND")*E11/C11 -> 8000 | J11: 0 | K11: =ROUND(F11*E11/C11,0) -> 45000 | L11: =SUM(G11:K11) -> 75500 | M11: =F11*12/100 -> 5400 | N11: =L11*75/10000 -> 566.25 | O11: 208 | P11: =L11*3/100 -> 2265 | Q11: 500 | R11: Loan/Advance EMI recovery | S11: =M11+N11+O11+P11+Q11 -> 8939.25 | T11: =L11-S11 -> 66560.75
A12: EMP001 | B12: 46054 | C12: =DAY(EOMONTH(B12,0)) -> 28 | D12: 2 | E12: =C12-D12 -> 26 | F12: =_xlfn.XLOOKUP(A12,'Salary Structure'!A:A,'Salary Structure'!B:B,"NOT FOUND") -> 30000 | G12: =_xlfn.XLOOKUP(A12,'Salary Structure'!A:A,'Salary Structure'!C:C,"NOT FOUND")*E12/C12 -> 11142.857 | H12: =_xlfn.XLOOKUP(A12,'Salary Structure'!A:A,'Salary Structure'!D:D,"NOT FOUND")*E12/C12 -> 2785.7143 | I12: =_xlfn.XLOOKUP(A12,'Salary Structure'!A:A,'Salary Structure'!E:E,"NOT FOUND")*E12/C12 -> 4642.8571 | J12: 0 | K12: =ROUND(F12*E12/C12,0) -> 27857 | L12: =SUM(G12:K12) -> 46428.429 | M12: =F12*12/100 -> 3600 | N12: =L12*75/10000 -> 348.21321 | O12: 208 | P12: =L12*3/100 -> 1392.8529 | Q12: 0 | S12: =M12+N12+O12+P12+Q12 -> 5549.0661 | T12: =L12-S12 -> 40879.363
A13: EMP002 | B13: 46054 | C13: =DAY(EOMONTH(B13,0)) -> 28 | D13: 2 | E13: =C13-D13 -> 26 | F13: =_xlfn.XLOOKUP(A13,'Salary Structure'!A:A,'Salary Structure'!B:B,"NOT FOUND") -> 25000 | G13: =_xlfn.XLOOKUP(A13,'Salary Structure'!A:A,'Salary Structure'!C:C,"NOT FOUND")*E13/C13 -> 9285.7143 | H13: =_xlfn.XLOOKUP(A13,'Salary Structure'!A:A,'Salary Structure'!D:D,"NOT FOUND")*E13/C13 -> 2321.4286 | I13: =_xlfn.XLOOKUP(A13,'Salary Structure'!A:A,'Salary Structure'!E:E,"NOT FOUND")*E13/C13 -> 3714.2857 | J13: 0 | K13: =ROUND(F13*E13/C13,0) -> 23214 | L13: =SUM(G13:K13) -> 38535.429 | M13: =F13*12/100 -> 3000 | N13: =L13*75/10000 -> 289.01571 | O13: 208 | P13: =L13*3/100 -> 1156.0629 | Q13: 0 | S13: =M13+N13+O13+P13+Q13 -> 4653.0786 | T13: =L13-S13 -> 33882.35
A14: EMP003 | B14: 46054 | C14: =DAY(EOMONTH(B14,0)) -> 28 | D14: 6 | E14: =C14-D14 -> 22 | F14: =_xlfn.XLOOKUP(A14,'Salary Structure'!A:A,'Salary Structure'!B:B,"NOT FOUND") -> 28000 | G14: =_xlfn.XLOOKUP(A14,'Salary Structure'!A:A,'Salary Structure'!C:C,"NOT FOUND")*E14/C14 -> 8800 | H14: =_xlfn.XLOOKUP(A14,'Salary Structure'!A:A,'Salary Structure'!D:D,"NOT FOUND")*E14/C14 -> 2200 | I14: =_xlfn.XLOOKUP(A14,'Salary Structure'!A:A,'Salary Structure'!E:E,"NOT FOUND")*E14/C14 -> 3535.7143 | J14: 0 | K14: =ROUND(F14*E14/C14,0) -> 22000 | L14: =SUM(G14:K14) -> 36535.714 | M14: =F14*12/100 -> 3360 | N14: =L14*75/10000 -> 274.01786 | O14: 208 | P14: =L14*3/100 -> 1096.0714 | Q14: 300 | R14: Loan/Advance EMI recovery | S14: =M14+N14+O14+P14+Q14 -> 5238.0893 | T14: =L14-S14 -> 31297.625
A15: EMP004 | B15: 46054 | C15: =DAY(EOMONTH(B15,0)) -> 28 | D15: 2 | E15: =C15-D15 -> 26 | F15: =_xlfn.XLOOKUP(A15,'Salary Structure'!A:A,'Salary Structure'!B:B,"NOT FOUND") -> 26000 | G15: =_xlfn.XLOOKUP(A15,'Salary Structure'!A:A,'Salary Structure'!C:C,"NOT FOUND")*E15/C15 -> 9657.1429 | H15: =_xlfn.XLOOKUP(A15,'Salary Structure'!A:A,'Salary Structure'!D:D,"NOT FOUND")*E15/C15 -> 2414.2857 | I15: =_xlfn.XLOOKUP(A15,'Salary Structure'!A:A,'Salary Structure'!E:E,"NOT FOUND")*E15/C15 -> 3714.2857 | J15: 0 | K15: =ROUND(F15*E15/C15,0) -> 24143 | L15: =SUM(G15:K15) -> 39928.714 | M15: =F15*12/100 -> 3120 | N15: =L15*75/10000 -> 299.46536 | O15: 208 | P15: =L15*3/100 -> 1197.8614 | Q15: 0 | S15: =M15+N15+O15+P15+Q15 -> 4825.3268 | T15: =L15-S15 -> 35103.387
A16: EMP005 | B16: 46054 | C16: =DAY(EOMONTH(B16,0)) -> 28 | D16: 0 | E16: =C16-D16 -> 28 | F16: =_xlfn.XLOOKUP(A16,'Salary Structure'!A:A,'Salary Structure'!B:B,"NOT FOUND") -> 32000 | G16: =_xlfn.XLOOKUP(A16,'Salary Structure'!A:A,'Salary Structure'!C:C,"NOT FOUND")*E16/C16 -> 12800 | H16: =_xlfn.XLOOKUP(A16,'Salary Structure'!A:A,'Salary Structure'!D:D,"NOT FOUND")*E16/C16 -> 3200 | I16: =_xlfn.XLOOKUP(A16,'Salary Structure'!A:A,'Salary Structure'!E:E,"NOT FOUND")*E16/C16 -> 5500 | J16: 0 | K16: =ROUND(F16*E16/C16,0) -> 32000 | L16: =SUM(G16:K16) -> 53500 | M16: =F16*12/100 -> 3840 | N16: =L16*75/10000 -> 401.25 | O16: 208 | P16: =L16*3/100 -> 1605 | Q16: 0 | S16: =M16+N16+O16+P16+Q16 -> 6054.25 | T16: =L16-S16 -> 47445.75
A17: EMP006 | B17: 46054 | C17: =DAY(EOMONTH(B17,0)) -> 28 | D17: 2 | E17: =C17-D17 -> 26 | F17: =_xlfn.XLOOKUP(A17,'Salary Structure'!A:A,'Salary Structure'!B:B,"NOT FOUND") -> 24000 | G17: =_xlfn.XLOOKUP(A17,'Salary Structure'!A:A,'Salary Structure'!C:C,"NOT FOUND")*E17/C17 -> 8914.2857 | H17: =_xlfn.XLOOKUP(A17,'Salary Structure'!A:A,'Salary Structure'!D:D,"NOT FOUND")*E17/C17 -> 2228.5714 | I17: =_xlfn.XLOOKUP(A17,'Salary Structure'!A:A,'Salary Structure'!E:E,"NOT FOUND")*E17/C17 -> 3250 | J17: 0 | K17: =ROUND(F17*E17/C17,0) -> 22286 | L17: =SUM(G17:K17) -> 36678.857 | M17: =F17*12/100 -> 2880 | N17: =L17*75/10000 -> 275.09143 | O17: 208 | P17: =L17*3/100 -> 1100.3657 | Q17: 0 | S17: =M17+N17+O17+P17+Q17 -> 4463.4571 | T17: =L17-S17 -> 32215.4
A18: EMP007 | B18: 46054 | C18: =DAY(EOMONTH(B18,0)) -> 28 | D18: 0 | E18: =C18-D18 -> 28 | F18: =_xlfn.XLOOKUP(A18,'Salary Structure'!A:A,'Salary Structure'!B:B,"NOT FOUND") -> 40000 | G18: =_xlfn.XLOOKUP(A18,'Salary Structure'!A:A,'Salary Structure'!C:C,"NOT FOUND")*E18/C18 -> 16000 | H18: =_xlfn.XLOOKUP(A18,'Salary Structure'!A:A,'Salary Structure'!D:D,"NOT FOUND")*E18/C18 -> 4000 | I18: =_xlfn.XLOOKUP(A18,'Salary Structure'!A:A,'Salary Structure'!E:E,"NOT FOUND")*E18/C18 -> 7000 | J18: 0 | K18: =ROUND(F18*E18/C18,0) -> 40000 | L18: =SUM(G18:K18) -> 67000 | M18: =F18*12/100 -> 4800 | N18: =L18*75/10000 -> 502.5 | O18: 208 | P18: =L18*3/100 -> 2010 | Q18: 0 | S18: =M18+N18+O18+P18+Q18 -> 7520.5 | T18: =L18-S18 -> 59479.5
A19: EMP008 | B19: 46054 | C19: =DAY(EOMONTH(B19,0)) -> 28 | D19: 6 | E19: =C19-D19 -> 22 | F19: =_xlfn.XLOOKUP(A19,'Salary Structure'!A:A,'Salary Structure'!B:B,"NOT FOUND") -> 30000 | G19: =_xlfn.XLOOKUP(A19,'Salary Structure'!A:A,'Salary Structure'!C:C,"NOT FOUND")*E19/C19 -> 9428.5714 | H19: =_xlfn.XLOOKUP(A19,'Salary Structure'!A:A,'Salary Structure'!D:D,"NOT FOUND")*E19/C19 -> 2357.1429 | I19: =_xlfn.XLOOKUP(A19,'Salary Structure'!A:A,'Salary Structure'!E:E,"NOT FOUND")*E19/C19 -> 3928.5714 | J19: 0 | K19: =ROUND(F19*E19/C19,0) -> 23571 | L19: =SUM(G19:K19) -> 39285.286 | M19: =F19*12/100 -> 3600 | N19: =L19*75/10000 -> 294.63964 | O19: 208 | P19: =L19*3/100 -> 1178.5586 | Q19: 0 | S19: =M19+N19+O19+P19+Q19 -> 5281.1982 | T19: =L19-S19 -> 34004.087
A20: EMP009 | B20: 46054 | C20: =DAY(EOMONTH(B20,0)) -> 28 | D20: 4 | E20: =C20-D20 -> 24 | F20: =_xlfn.XLOOKUP(A20,'Salary Structure'!A:A,'Salary Structure'!B:B,"NOT FOUND") -> 23000 | G20: =_xlfn.XLOOKUP(A20,'Salary Structure'!A:A,'Salary Structure'!C:C,"NOT FOUND")*E20/C20 -> 7885.7143 | H20: =_xlfn.XLOOKUP(A20,'Salary Structure'!A:A,'Salary Structure'!D:D,"NOT FOUND")*E20/C20 -> 1971.4286 | I20: =_xlfn.XLOOKUP(A20,'Salary Structure'!A:A,'Salary Structure'!E:E,"NOT FOUND")*E20/C20 -> 3000 | J20: 0 | K20: =ROUND(F20*E20/C20,0) -> 19714 | L20: =SUM(G20:K20) -> 32571.143 | M20: =F20*12/100 -> 2760 | N20: =L20*75/10000 -> 244.28357 | O20: 208 | P20: =L20*3/100 -> 977.13429 | Q20: 0 | S20: =M20+N20+O20+P20+Q20 -> 4189.4179 | T20: =L20-S20 -> 28381.725
A21: EMP010 | B21: 46054 | C21: =DAY(EOMONTH(B21,0)) -> 28 | D21: 1 | E21: =C21-D21 -> 27 | F21: =_xlfn.XLOOKUP(A21,'Salary Structure'!A:A,'Salary Structure'!B:B,"NOT FOUND") -> 45000 | G21: =_xlfn.XLOOKUP(A21,'Salary Structure'!A:A,'Salary Structure'!C:C,"NOT FOUND")*E21/C21 -> 17357.143 | H21: =_xlfn.XLOOKUP(A21,'Salary Structure'!A:A,'Salary Structure'!D:D,"NOT FOUND")*E21/C21 -> 4339.2857 | I21: =_xlfn.XLOOKUP(A21,'Salary Structure'!A:A,'Salary Structure'!E:E,"NOT FOUND")*E21/C21 -> 7714.2857 | J21: 1500 | K21: =ROUND(F21*E21/C21,0) -> 43393 | L21: =SUM(G21:K21) -> 74303.714 | M21: =F21*12/100 -> 5400 | N21: =L21*75/10000 -> 557.27786 | O21: 208 | P21: =L21*3/100 -> 2229.1114 | Q21: 500 | R21: Loan/Advance EMI recovery | S21: =M21+N21+O21+P21+Q21 -> 8894.3893 | T21: =L21-S21 -> 65409.325
A22: EMP001 | B22: 46082 | C22: =DAY(EOMONTH(B22,0)) -> 31 | D22: 0 | E22: =C22-D22 -> 31 | F22: =_xlfn.XLOOKUP(A22,'Salary Structure'!A:A,'Salary Structure'!B:B,"NOT FOUND") -> 30000 | G22: =_xlfn.XLOOKUP(A22,'Salary Structure'!A:A,'Salary Structure'!C:C,"NOT FOUND")*E22/C22 -> 12000 | H22: =_xlfn.XLOOKUP(A22,'Salary Structure'!A:A,'Salary Structure'!D:D,"NOT FOUND")*E22/C22 -> 3000 | I22: =_xlfn.XLOOKUP(A22,'Salary Structure'!A:A,'Salary Structure'!E:E,"NOT FOUND")*E22/C22 -> 5000 | J22: 0 | K22: =ROUND(F22*E22/C22,0) -> 30000 | L22: =SUM(G22:K22) -> 50000 | M22: =F22*12/100 -> 3600 | N22: =L22*75/10000 -> 375 | O22: 212 | P22: =L22*3/100 -> 1500 | Q22: 0 | S22: =M22+N22+O22+P22+Q22 -> 5687 | T22: =L22-S22 -> 44313
A23: EMP002 | B23: 46082 | C23: =DAY(EOMONTH(B23,0)) -> 31 | D23: 2 | E23: =C23-D23 -> 29 | F23: =_xlfn.XLOOKUP(A23,'Salary Structure'!A:A,'Salary Structure'!B:B,"NOT FOUND") -> 25000 | G23: =_xlfn.XLOOKUP(A23,'Salary Structure'!A:A,'Salary Structure'!C:C,"NOT FOUND")*E23/C23 -> 9354.8387 | H23: =_xlfn.XLOOKUP(A23,'Salary Structure'!A:A,'Salary Structure'!D:D,"NOT FOUND")*E23/C23 -> 2338.7097 | I23: =_xlfn.XLOOKUP(A23,'Salary Structure'!A:A,'Salary Structure'!E:E,"NOT FOUND")*E23/C23 -> 3741.9355 | J23: 0 | K23: =ROUND(F23*E23/C23,0) -> 23387 | L23: =SUM(G23:K23) -> 38822.484 | M23: =F23*12/100 -> 3000 | N23: =L23*75/10000 -> 291.16863 | O23: 212 | P23: =L23*3/100 -> 1164.6745 | Q23: 0 | S23: =M23+N23+O23+P23+Q23 -> 4667.8431 | T23: =L23-S23 -> 34154.641
A24: EMP003 | B24: 46082 | C24: =DAY(EOMONTH(B24,0)) -> 31 | D24: 0 | E24: =C24-D24 -> 31 | F24: =_xlfn.XLOOKUP(A24,'Salary Structure'!A:A,'Salary Structure'!B:B,"NOT FOUND") -> 28000 | G24: =_xlfn.XLOOKUP(A24,'Salary Structure'!A:A,'Salary Structure'!C:C,"NOT FOUND")*E24/C24 -> 11200 | H24: =_xlfn.XLOOKUP(A24,'Salary Structure'!A:A,'Salary Structure'!D:D,"NOT FOUND")*E24/C24 -> 2800 | I24: =_xlfn.XLOOKUP(A24,'Salary Structure'!A:A,'Salary Structure'!E:E,"NOT FOUND")*E24/C24 -> 4500 | J24: 0 | K24: =ROUND(F24*E24/C24,0) -> 28000 | L24: =SUM(G24:K24) -> 46500 | M24: =F24*12/100 -> 3360 | N24: =L24*75/10000 -> 348.75 | O24: 212 | P24: =L24*3/100 -> 1395 | Q24: 300 | R24: Loan/Advance EMI recovery | S24: =M24+N24+O24+P24+Q24 -> 5615.75 | T24: =L24-S24 -> 40884.25
A25: EMP004 | B25: 46082 | C25: =DAY(EOMONTH(B25,0)) -> 31 | D25: 0 | E25: =C25-D25 -> 31 | F25: =_xlfn.XLOOKUP(A25,'Salary Structure'!A:A,'Salary Structure'!B:B,"NOT FOUND") -> 26000 | G25: =_xlfn.XLOOKUP(A25,'Salary Structure'!A:A,'Salary Structure'!C:C,"NOT FOUND")*E25/C25 -> 10400 | H25: =_xlfn.XLOOKUP(A25,'Salary Structure'!A:A,'Salary Structure'!D:D,"NOT FOUND")*E25/C25 -> 2600 | I25: =_xlfn.XLOOKUP(A25,'Salary Structure'!A:A,'Salary Structure'!E:E,"NOT FOUND")*E25/C25 -> 4000 | J25: 0 | K25: =ROUND(F25*E25/C25,0) -> 26000 | L25: =SUM(G25:K25) -> 43000 | M25: =F25*12/100 -> 3120 | N25: =L25*75/10000 -> 322.5 | O25: 212 | P25: =L25*3/100 -> 1290 | Q25: 0 | S25: =M25+N25+O25+P25+Q25 -> 4944.5 | T25: =L25-S25 -> 38055.5
A26: EMP005 | B26: 46082 | C26: =DAY(EOMONTH(B26,0)) -> 31 | D26: 7 | E26: =C26-D26 -> 24 | F26: =_xlfn.XLOOKUP(A26,'Salary Structure'!A:A,'Salary Structure'!B:B,"NOT FOUND") -> 32000 | G26: =_xlfn.XLOOKUP(A26,'Salary Structure'!A:A,'Salary Structure'!C:C,"NOT FOUND")*E26/C26 -> 9909.6774 | H26: =_xlfn.XLOOKUP(A26,'Salary Structure'!A:A,'Salary Structure'!D:D,"NOT FOUND")*E26/C26 -> 2477.4194 | I26: =_xlfn.XLOOKUP(A26,'Salary Structure'!A:A,'Salary Structure'!E:E,"NOT FOUND")*E26/C26 -> 4258.0645 | J26: 0 | K26: =ROUND(F26*E26/C26,0) -> 24774 | L26: =SUM(G26:K26) -> 41419.161 | M26: =F26*12/100 -> 3840 | N26: =L26*75/10000 -> 310.64371 | O26: 212 | P26: =L26*3/100 -> 1242.5748 | Q26: 0 | S26: =M26+N26+O26+P26+Q26 -> 5605.2185 | T26: =L26-S26 -> 35813.943
A27: EMP006 | B27: 46082 | C27: =DAY(EOMONTH(B27,0)) -> 31 | D27: 0 | E27: =C27-D27 -> 31 | F27: =_xlfn.XLOOKUP(A27,'Salary Structure'!A:A,'Salary Structure'!B:B,"NOT FOUND") -> 24000 | G27: =_xlfn.XLOOKUP(A27,'Salary Structure'!A:A,'Salary Structure'!C:C,"NOT FOUND")*E27/C27 -> 9600 | H27: =_xlfn.XLOOKUP(A27,'Salary Structure'!A:A,'Salary Structure'!D:D,"NOT FOUND")*E27/C27 -> 2400 | I27: =_xlfn.XLOOKUP(A27,'Salary Structure'!A:A,'Salary Structure'!E:E,"NOT FOUND")*E27/C27 -> 3500 | J27: 0 | K27: =ROUND(F27*E27/C27,0) -> 24000 | L27: =SUM(G27:K27) -> 39500 | M27: =F27*12/100 -> 2880 | N27: =L27*75/10000 -> 296.25 | O27: 212 | P27: =L27*3/100 -> 1185 | Q27: 0 | S27: =M27+N27+O27+P27+Q27 -> 4573.25 | T27: =L27-S27 -> 34926.75
A28: EMP007 | B28: 46082 | C28: =DAY(EOMONTH(B28,0)) -> 31 | D28: 4 | E28: =C28-D28 -> 27 | F28: =_xlfn.XLOOKUP(A28,'Salary Structure'!A:A,'Salary Structure'!B:B,"NOT FOUND") -> 40000 | G28: =_xlfn.XLOOKUP(A28,'Salary Structure'!A:A,'Salary Structure'!C:C,"NOT FOUND")*E28/C28 -> 13935.484 | H28: =_xlfn.XLOOKUP(A28,'Salary Structure'!A:A,'Salary Structure'!D:D,"NOT FOUND")*E28/C28 -> 3483.871 | I28: =_xlfn.XLOOKUP(A28,'Salary Structure'!A:A,'Salary Structure'!E:E,"NOT FOUND")*E28/C28 -> 6096.7742 | J28: 0 | K28: =ROUND(F28*E28/C28,0) -> 34839 | L28: =SUM(G28:K28) -> 58355.129 | M28: =F28*12/100 -> 4800 | N28: =L28*75/10000 -> 437.66347 | O28: 212 | P28: =L28*3/100 -> 1750.6539 | Q28: 0 | S28: =M28+N28+O28+P28+Q28 -> 7200.3173 | T28: =L28-S28 -> 51154.812
A29: EMP008 | B29: 46082 | C29: =DAY(EOMONTH(B29,0)) -> 31 | D29: 0 | E29: =C29-D29 -> 31 | F29: =_xlfn.XLOOKUP(A29,'Salary Structure'!A:A,'Salary Structure'!B:B,"NOT FOUND") -> 30000 | G29: =_xlfn.XLOOKUP(A29,'Salary Structure'!A:A,'Salary Structure'!C:C,"NOT FOUND")*E29/C29 -> 12000 | H29: =_xlfn.XLOOKUP(A29,'Salary Structure'!A:A,'Salary Structure'!D:D,"NOT FOUND")*E29/C29 -> 3000 | I29: =_xlfn.XLOOKUP(A29,'Salary Structure'!A:A,'Salary Structure'!E:E,"NOT FOUND")*E29/C29 -> 5000 | J29: 0 | K29: =ROUND(F29*E29/C29,0) -> 30000 | L29: =SUM(G29:K29) -> 50000 | M29: =F29*12/100 -> 3600 | N29: =L29*75/10000 -> 375 | O29: 212 | P29: =L29*3/100 -> 1500 | Q29: 0 | S29: =M29+N29+O29+P29+Q29 -> 5687 | T29: =L29-S29 -> 44313
A30: EMP009 | B30: 46082 | C30: =DAY(EOMONTH(B30,0)) -> 31 | D30: 0 | E30: =C30-D30 -> 31 | F30: =_xlfn.XLOOKUP(A30,'Salary Structure'!A:A,'Salary Structure'!B:B,"NOT FOUND") -> 23000 | G30: =_xlfn.XLOOKUP(A30,'Salary Structure'!A:A,'Salary Structure'!C:C,"NOT FOUND")*E30/C30 -> 9200 | H30: =_xlfn.XLOOKUP(A30,'Salary Structure'!A:A,'Salary Structure'!D:D,"NOT FOUND")*E30/C30 -> 2300 | I30: =_xlfn.XLOOKUP(A30,'Salary Structure'!A:A,'Salary Structure'!E:E,"NOT FOUND")*E30/C30 -> 3500 | J30: 0 | K30: =ROUND(F30*E30/C30,0) -> 23000 | L30: =SUM(G30:K30) -> 38000 | M30: =F30*12/100 -> 2760 | N30: =L30*75/10000 -> 285 | O30: 212 | P30: =L30*3/100 -> 1140 | Q30: 0 | S30: =M30+N30+O30+P30+Q30 -> 4397 | T30: =L30-S30 -> 33603
A31: EMP010 | B31: 46082 | C31: =DAY(EOMONTH(B31,0)) -> 31 | D31: 0 | E31: =C31-D31 -> 31 | F31: =_xlfn.XLOOKUP(A31,'Salary Structure'!A:A,'Salary Structure'!B:B,"NOT FOUND") -> 45000 | G31: =_xlfn.XLOOKUP(A31,'Salary Structure'!A:A,'Salary Structure'!C:C,"NOT FOUND")*E31/C31 -> 18000 | H31: =_xlfn.XLOOKUP(A31,'Salary Structure'!A:A,'Salary Structure'!D:D,"NOT FOUND")*E31/C31 -> 4500 | I31: =_xlfn.XLOOKUP(A31,'Salary Structure'!A:A,'Salary Structure'!E:E,"NOT FOUND")*E31/C31 -> 8000 | J31: 0 | K31: =ROUND(F31*E31/C31,0) -> 45000 | L31: =SUM(G31:K31) -> 75500 | M31: =F31*12/100 -> 5400 | N31: =L31*75/10000 -> 566.25 | O31: 212 | P31: =L31*3/100 -> 2265 | Q31: 500 | R31: Loan/Advance EMI recovery | S31: =M31+N31+O31+P31+Q31 -> 8943.25 | T31: =L31-S31 -> 66556.75
A32: EMP001 | B32: 46113 | C32: =DAY(EOMONTH(B32,0)) -> 30 | D32: 4 | E32: =C32-D32 -> 26 | F32: =_xlfn.XLOOKUP(A32,'Salary Structure'!A:A,'Salary Structure'!B:B,"NOT FOUND") -> 30000 | G32: =_xlfn.XLOOKUP(A32,'Salary Structure'!A:A,'Salary Structure'!C:C,"NOT FOUND")*E32/C32 -> 10400 | H32: =_xlfn.XLOOKUP(A32,'Salary Structure'!A:A,'Salary Structure'!D:D,"NOT FOUND")*E32/C32 -> 2600 | I32: =_xlfn.XLOOKUP(A32,'Salary Structure'!A:A,'Salary Structure'!E:E,"NOT FOUND")*E32/C32 -> 4333.3333 | J32: 0 | K32: =ROUND(F32*E32/C32,0) -> 26000 | L32: =SUM(G32:K32) -> 43333.333 | M32: =F32*12/100 -> 3600 | N32: =L32*75/10000 -> 325 | O32: 208 | P32: =L32*3/100 -> 1300 | Q32: 0 | S32: =M32+N32+O32+P32+Q32 -> 5433 | T32: =L32-S32 -> 37900.333
A33: EMP002 | B33: 46113 | C33: =DAY(EOMONTH(B33,0)) -> 30 | D33: 3 | E33: =C33-D33 -> 27 | F33: =_xlfn.XLOOKUP(A33,'Salary Structure'!A:A,'Salary Structure'!B:B,"NOT FOUND") -> 25000 | G33: =_xlfn.XLOOKUP(A33,'Salary Structure'!A:A,'Salary Structure'!C:C,"NOT FOUND")*E33/C33 -> 9000 | H33: =_xlfn.XLOOKUP(A33,'Salary Structure'!A:A,'Salary Structure'!D:D,"NOT FOUND")*E33/C33 -> 2250 | I33: =_xlfn.XLOOKUP(A33,'Salary Structure'!A:A,'Salary Structure'!E:E,"NOT FOUND")*E33/C33 -> 3600 | J33: 0 | K33: =ROUND(F33*E33/C33,0) -> 22500 | L33: =SUM(G33:K33) -> 37350 | M33: =F33*12/100 -> 3000 | N33: =L33*75/10000 -> 280.125 | O33: 208 | P33: =L33*3/100 -> 1120.5 | Q33: 0 | S33: =M33+N33+O33+P33+Q33 -> 4608.625 | T33: =L33-S33 -> 32741.375
A34: EMP003 | B34: 46113 | C34: =DAY(EOMONTH(B34,0)) -> 30 | D34: 0 | E34: =C34-D34 -> 30 | F34: =_xlfn.XLOOKUP(A34,'Salary Structure'!A:A,'Salary Structure'!B:B,"NOT FOUND") -> 28000 | G34: =_xlfn.XLOOKUP(A34,'Salary Structure'!A:A,'Salary Structure'!C:C,"NOT FOUND")*E34/C34 -> 11200 | H34: =_xlfn.XLOOKUP(A34,'Salary Structure'!A:A,'Salary Structure'!D:D,"NOT FOUND")*E34/C34 -> 2800 | I34: =_xlfn.XLOOKUP(A34,'Salary Structure'!A:A,'Salary Structure'!E:E,"NOT FOUND")*E34/C34 -> 4500 | J34: 0 | K34: =ROUND(F34*E34/C34,0) -> 28000 | L34: =SUM(G34:K34) -> 46500 | M34: =F34*12/100 -> 3360 | N34: =L34*75/10000 -> 348.75 | O34: 208 | P34: =L34*3/100 -> 1395 | Q34: 300 | R34: Loan/Advance EMI recovery | S34: =M34+N34+O34+P34+Q34 -> 5611.75 | T34: =L34-S34 -> 40888.25
A35: EMP004 | B35: 46113 | C35: =DAY(EOMONTH(B35,0)) -> 30 | D35: 2 | E35: =C35-D35 -> 28 | F35: =_xlfn.XLOOKUP(A35,'Salary Structure'!A:A,'Salary Structure'!B:B,"NOT FOUND") -> 26000 | G35: =_xlfn.XLOOKUP(A35,'Salary Structure'!A:A,'Salary Structure'!C:C,"NOT FOUND")*E35/C35 -> 9706.6667 | H35: =_xlfn.XLOOKUP(A35,'Salary Structure'!A:A,'Salary Structure'!D:D,"NOT FOUND")*E35/C35 -> 2426.6667 | I35: =_xlfn.XLOOKUP(A35,'Salary Structure'!A:A,'Salary Structure'!E:E,"NOT FOUND")*E35/C35 -> 3733.3333 | J35: 0 | K35: =ROUND(F35*E35/C35,0) -> 24267 | L35: =SUM(G35:K35) -> 40133.667 | M35: =F35*12/100 -> 3120 | N35: =L35*75/10000 -> 301.0025 | O35: 208 | P35: =L35*3/100 -> 1204.01 | Q35: 0 | S35: =M35+N35+O35+P35+Q35 -> 4833.0125 | T35: =L35-S35 -> 35300.654
A36: EMP005 | B36: 46113 | C36: =DAY(EOMONTH(B36,0)) -> 30 | D36: 3 | E36: =C36-D36 -> 27 | F36: =_xlfn.XLOOKUP(A36,'Salary Structure'!A:A,'Salary Structure'!B:B,"NOT FOUND") -> 32000 | G36: =_xlfn.XLOOKUP(A36,'Salary Structure'!A:A,'Salary Structure'!C:C,"NOT FOUND")*E36/C36 -> 11520 | H36: =_xlfn.XLOOKUP(A36,'Salary Structure'!A:A,'Salary Structure'!D:D,"NOT FOUND")*E36/C36 -> 2880 | I36: =_xlfn.XLOOKUP(A36,'Salary Structure'!A:A,'Salary Structure'!E:E,"NOT FOUND")*E36/C36 -> 4950 | J36: 2000 | K36: =ROUND(F36*E36/C36,0) -> 28800 | L36: =SUM(G36:K36) -> 50150 | M36: =F36*12/100 -> 3840 | N36: =L36*75/10000 -> 376.125 | O36: 208 | P36: =L36*3/100 -> 1504.5 | Q36: 0 | S36: =M36+N36+O36+P36+Q36 -> 5928.625 | T36: =L36-S36 -> 44221.375
A37: EMP006 | B37: 46113 | C37: =DAY(EOMONTH(B37,0)) -> 30 | D37: 0 | E37: =C37-D37 -> 30 | F37: =_xlfn.XLOOKUP(A37,'Salary Structure'!A:A,'Salary Structure'!B:B,"NOT FOUND") -> 24000 | G37: =_xlfn.XLOOKUP(A37,'Salary Structure'!A:A,'Salary Structure'!C:C,"NOT FOUND")*E37/C37 -> 9600 | H37: =_xlfn.XLOOKUP(A37,'Salary Structure'!A:A,'Salary Structure'!D:D,"NOT FOUND")*E37/C37 -> 2400 | I37: =_xlfn.XLOOKUP(A37,'Salary Structure'!A:A,'Salary Structure'!E:E,"NOT FOUND")*E37/C37 -> 3500 | J37: 0 | K37: =ROUND(F37*E37/C37,0) -> 24000 | L37: =SUM(G37:K37) -> 39500 | M37: =F37*12/100 -> 2880 | N37: =L37*75/10000 -> 296.25 | O37: 208 | P37: =L37*3/100 -> 1185 | Q37: 0 | S37: =M37+N37+O37+P37+Q37 -> 4569.25 | T37: =L37-S37 -> 34930.75
A38: EMP007 | B38: 46113 | C38: =DAY(EOMONTH(B38,0)) -> 30 | D38: 0 | E38: =C38-D38 -> 30 | F38: =_xlfn.XLOOKUP(A38,'Salary Structure'!A:A,'Salary Structure'!B:B,"NOT FOUND") -> 40000 | G38: =_xlfn.XLOOKUP(A38,'Salary Structure'!A:A,'Salary Structure'!C:C,"NOT FOUND")*E38/C38 -> 16000 | H38: =_xlfn.XLOOKUP(A38,'Salary Structure'!A:A,'Salary Structure'!D:D,"NOT FOUND")*E38/C38 -> 4000 | I38: =_xlfn.XLOOKUP(A38,'Salary Structure'!A:A,'Salary Structure'!E:E,"NOT FOUND")*E38/C38 -> 7000 | J38: 0 | K38: =ROUND(F38*E38/C38,0) -> 40000 | L38: =SUM(G38:K38) -> 67000 | M38: =F38*12/100 -> 4800 | N38: =L38*75/10000 -> 502.5 | O38: 208 | P38: =L38*3/100 -> 2010 | Q38: 0 | S38: =M38+N38+O38+P38+Q38 -> 7520.5 | T38: =L38-S38 -> 59479.5
A39: EMP008 | B39: 46113 | C39: =DAY(EOMONTH(B39,0)) -> 30 | D39: 0 | E39: =C39-D39 -> 30 | F39: =_xlfn.XLOOKUP(A39,'Salary Structure'!A:A,'Salary Structure'!B:B,"NOT FOUND") -> 30000 | G39: =_xlfn.XLOOKUP(A39,'Salary Structure'!A:A,'Salary Structure'!C:C,"NOT FOUND")*E39/C39 -> 12000 | H39: =_xlfn.XLOOKUP(A39,'Salary Structure'!A:A,'Salary Structure'!D:D,"NOT FOUND")*E39/C39 -> 3000 | I39: =_xlfn.XLOOKUP(A39,'Salary Structure'!A:A,'Salary Structure'!E:E,"NOT FOUND")*E39/C39 -> 5000 | J39: 0 | K39: =ROUND(F39*E39/C39,0) -> 30000 | L39: =SUM(G39:K39) -> 50000 | M39: =F39*12/100 -> 3600 | N39: =L39*75/10000 -> 375 | O39: 208 | P39: =L39*3/100 -> 1500 | Q39: 0 | S39: =M39+N39+O39+P39+Q39 -> 5683 | T39: =L39-S39 -> 44317
A40: EMP009 | B40: 46113 | C40: =DAY(EOMONTH(B40,0)) -> 30 | D40: 2 | E40: =C40-D40 -> 28 | F40: =_xlfn.XLOOKUP(A40,'Salary Structure'!A:A,'Salary Structure'!B:B,"NOT FOUND") -> 23000 | G40: =_xlfn.XLOOKUP(A40,'Salary Structure'!A:A,'Salary Structure'!C:C,"NOT FOUND")*E40/C40 -> 8586.6667 | H40: =_xlfn.XLOOKUP(A40,'Salary Structure'!A:A,'Salary Structure'!D:D,"NOT FOUND")*E40/C40 -> 2146.6667 | I40: =_xlfn.XLOOKUP(A40,'Salary Structure'!A:A,'Salary Structure'!E:E,"NOT FOUND")*E40/C40 -> 3266.6667 | J40: 0 | K40: =ROUND(F40*E40/C40,0) -> 21467 | L40: =SUM(G40:K40) -> 35467 | M40: =F40*12/100 -> 2760 | N40: =L40*75/10000 -> 266.0025 | O40: 208 | P40: =L40*3/100 -> 1064.01 | Q40: 0 | S40: =M40+N40+O40+P40+Q40 -> 4298.0125 | T40: =L40-S40 -> 31168.987
A41: EMP010 | B41: 46113 | C41: =DAY(EOMONTH(B41,0)) -> 30 | D41: 1 | E41: =C41-D41 -> 29 | F41: =_xlfn.XLOOKUP(A41,'Salary Structure'!A:A,'Salary Structure'!B:B,"NOT FOUND") -> 45000 | G41: =_xlfn.XLOOKUP(A41,'Salary Structure'!A:A,'Salary Structure'!C:C,"NOT FOUND")*E41/C41 -> 17400 | H41: =_xlfn.XLOOKUP(A41,'Salary Structure'!A:A,'Salary Structure'!D:D,"NOT FOUND")*E41/C41 -> 4350 | I41: =_xlfn.XLOOKUP(A41,'Salary Structure'!A:A,'Salary Structure'!E:E,"NOT FOUND")*E41/C41 -> 7733.3333 | J41: 0 | K41: =ROUND(F41*E41/C41,0) -> 43500 | L41: =SUM(G41:K41) -> 72983.333 | M41: =F41*12/100 -> 5400 | N41: =L41*75/10000 -> 547.375 | O41: 208 | P41: =L41*3/100 -> 2189.5 | Q41: 500 | R41: Loan/Advance EMI recovery | S41: =M41+N41+O41+P41+Q41 -> 8844.875 | T41: =L41-S41 -> 64138.458
A42: EMP001 | B42: 46143 | C42: =DAY(EOMONTH(B42,0)) -> 31 | D42: 4 | E42: =C42-D42 -> 27 | F42: =_xlfn.XLOOKUP(A42,'Salary Structure'!A:A,'Salary Structure'!B:B,"NOT FOUND") -> 30000 | G42: =_xlfn.XLOOKUP(A42,'Salary Structure'!A:A,'Salary Structure'!C:C,"NOT FOUND")*E42/C42 -> 10451.613 | H42: =_xlfn.XLOOKUP(A42,'Salary Structure'!A:A,'Salary Structure'!D:D,"NOT FOUND")*E42/C42 -> 2612.9032 | I42: =_xlfn.XLOOKUP(A42,'Salary Structure'!A:A,'Salary Structure'!E:E,"NOT FOUND")*E42/C42 -> 4354.8387 | J42: 0 | K42: =ROUND(F42*E42/C42,0) -> 26129 | L42: =SUM(G42:K42) -> 43548.355 | M42: =F42*12/100 -> 3600 | N42: =L42*75/10000 -> 326.61266 | O42: 208 | P42: =L42*3/100 -> 1306.4506 | Q42: 0 | S42: =M42+N42+O42+P42+Q42 -> 5441.0633 | T42: =L42-S42 -> 38107.292
A43: EMP002 | B43: 46143 | C43: =DAY(EOMONTH(B43,0)) -> 31 | D43: 0 | E43: =C43-D43 -> 31 | F43: =_xlfn.XLOOKUP(A43,'Salary Structure'!A:A,'Salary Structure'!B:B,"NOT FOUND") -> 25000 | G43: =_xlfn.XLOOKUP(A43,'Salary Structure'!A:A,'Salary Structure'!C:C,"NOT FOUND")*E43/C43 -> 10000 | H43: =_xlfn.XLOOKUP(A43,'Salary Structure'!A:A,'Salary Structure'!D:D,"NOT FOUND")*E43/C43 -> 2500 | I43: =_xlfn.XLOOKUP(A43,'Salary Structure'!A:A,'Salary Structure'!E:E,"NOT FOUND")*E43/C43 -> 4000 | J43: 0 | K43: =ROUND(F43*E43/C43,0) -> 25000 | L43: =SUM(G43:K43) -> 41500 | M43: =F43*12/100 -> 3000 | N43: =L43*75/10000 -> 311.25 | O43: 208 | P43: =L43*3/100 -> 1245 | Q43: 0 | S43: =M43+N43+O43+P43+Q43 -> 4764.25 | T43: =L43-S43 -> 36735.75
A44: EMP003 | B44: 46143 | C44: =DAY(EOMONTH(B44,0)) -> 31 | D44: 2 | E44: =C44-D44 -> 29 | F44: =_xlfn.XLOOKUP(A44,'Salary Structure'!A:A,'Salary Structure'!B:B,"NOT FOUND") -> 28000 | G44: =_xlfn.XLOOKUP(A44,'Salary Structure'!A:A,'Salary Structure'!C:C,"NOT FOUND")*E44/C44 -> 10477.419 | H44: =_xlfn.XLOOKUP(A44,'Salary Structure'!A:A,'Salary Structure'!D:D,"NOT FOUND")*E44/C44 -> 2619.3548 | I44: =_xlfn.XLOOKUP(A44,'Salary Structure'!A:A,'Salary Structure'!E:E,"NOT FOUND")*E44/C44 -> 4209.6774 | J44: 0 | K44: =ROUND(F44*E44/C44,0) -> 26194 | L44: =SUM(G44:K44) -> 43500.452 | M44: =F44*12/100 -> 3360 | N44: =L44*75/10000 -> 326.25339 | O44: 208 | P44: =L44*3/100 -> 1305.0135 | Q44: 300 | R44: Loan/Advance EMI recovery | S44: =M44+N44+O44+P44+Q44 -> 5499.2669 | T44: =L44-S44 -> 38001.185
A45: EMP004 | B45: 46143 | C45: =DAY(EOMONTH(B45,0)) -> 31 | D45: 4 | E45: =C45-D45 -> 27 | F45: =_xlfn.XLOOKUP(A45,'Salary Structure'!A:A,'Salary Structure'!B:B,"NOT FOUND") -> 26000 | G45: =_xlfn.XLOOKUP(A45,'Salary Structure'!A:A,'Salary Structure'!C:C,"NOT FOUND")*E45/C45 -> 9058.0645 | H45: =_xlfn.XLOOKUP(A45,'Salary Structure'!A:A,'Salary Structure'!D:D,"NOT FOUND")*E45/C45 -> 2264.5161 | I45: =_xlfn.XLOOKUP(A45,'Salary Structure'!A:A,'Salary Structure'!E:E,"NOT FOUND")*E45/C45 -> 3483.871 | J45: 0 | K45: =ROUND(F45*E45/C45,0) -> 22645 | L45: =SUM(G45:K45) -> 37451.452 | M45: =F45*12/100 -> 3120 | N45: =L45*75/10000 -> 280.88589 | O45: 208 | P45: =L45*3/100 -> 1123.5435 | Q45: 0 | S45: =M45+N45+O45+P45+Q45 -> 4732.4294 | T45: =L45-S45 -> 32719.022
A46: EMP005 | B46: 46143 | C46: =DAY(EOMONTH(B46,0)) -> 31 | D46: 0 | E46: =C46-D46 -> 31 | F46: =_xlfn.XLOOKUP(A46,'Salary Structure'!A:A,'Salary Structure'!B:B,"NOT FOUND") -> 32000 | G46: =_xlfn.XLOOKUP(A46,'Salary Structure'!A:A,'Salary Structure'!C:C,"NOT FOUND")*E46/C46 -> 12800 | H46: =_xlfn.XLOOKUP(A46,'Salary Structure'!A:A,'Salary Structure'!D:D,"NOT FOUND")*E46/C46 -> 3200 | I46: =_xlfn.XLOOKUP(A46,'Salary Structure'!A:A,'Salary Structure'!E:E,"NOT FOUND")*E46/C46 -> 5500 | J46: 0 | K46: =ROUND(F46*E46/C46,0) -> 32000 | L46: =SUM(G46:K46) -> 53500 | M46: =F46*12/100 -> 3840 | N46: =L46*75/10000 -> 401.25 | O46: 208 | P46: =L46*3/100 -> 1605 | Q46: 0 | S46: =M46+N46+O46+P46+Q46 -> 6054.25 | T46: =L46-S46 -> 47445.75
A47: EMP006 | B47: 46143 | C47: =DAY(EOMONTH(B47,0)) -> 31 | D47: 4 | E47: =C47-D47 -> 27 | F47: =_xlfn.XLOOKUP(A47,'Salary Structure'!A:A,'Salary Structure'!B:B,"NOT FOUND") -> 24000 | G47: =_xlfn.XLOOKUP(A47,'Salary Structure'!A:A,'Salary Structure'!C:C,"NOT FOUND")*E47/C47 -> 8361.2903 | H47: =_xlfn.XLOOKUP(A47,'Salary Structure'!A:A,'Salary Structure'!D:D,"NOT FOUND")*E47/C47 -> 2090.3226 | I47: =_xlfn.XLOOKUP(A47,'Salary Structure'!A:A,'Salary Structure'!E:E,"NOT FOUND")*E47/C47 -> 3048.3871 | J47: 0 | K47: =ROUND(F47*E47/C47,0) -> 20903 | L47: =SUM(G47:K47) -> 34403 | M47: =F47*12/100 -> 2880 | N47: =L47*75/10000 -> 258.0225 | O47: 208 | P47: =L47*3/100 -> 1032.09 | Q47: 0 | S47: =M47+N47+O47+P47+Q47 -> 4378.1125 | T47: =L47-S47 -> 30024.888
A48: EMP007 | B48: 46143 | C48: =DAY(EOMONTH(B48,0)) -> 31 | D48: 1 | E48: =C48-D48 -> 30 | F48: =_xlfn.XLOOKUP(A48,'Salary Structure'!A:A,'Salary Structure'!B:B,"NOT FOUND") -> 40000 | G48: =_xlfn.XLOOKUP(A48,'Salary Structure'!A:A,'Salary Structure'!C:C,"NOT FOUND")*E48/C48 -> 15483.871 | H48: =_xlfn.XLOOKUP(A48,'Salary Structure'!A:A,'Salary Structure'!D:D,"NOT FOUND")*E48/C48 -> 3870.9677 | I48: =_xlfn.XLOOKUP(A48,'Salary Structure'!A:A,'Salary Structure'!E:E,"NOT FOUND")*E48/C48 -> 6774.1935 | J48: 0 | K48: =ROUND(F48*E48/C48,0) -> 38710 | L48: =SUM(G48:K48) -> 64839.032 | M48: =F48*12/100 -> 4800 | N48: =L48*75/10000 -> 486.29274 | O48: 208 | P48: =L48*3/100 -> 1945.171 | Q48: 0 | S48: =M48+N48+O48+P48+Q48 -> 7439.4637 | T48: =L48-S48 -> 57399.569
A49: EMP008 | B49: 46143 | C49: =DAY(EOMONTH(B49,0)) -> 31 | D49: 1 | E49: =C49-D49 -> 30 | F49: =_xlfn.XLOOKUP(A49,'Salary Structure'!A:A,'Salary Structure'!B:B,"NOT FOUND") -> 30000 | G49: =_xlfn.XLOOKUP(A49,'Salary Structure'!A:A,'Salary Structure'!C:C,"NOT FOUND")*E49/C49 -> 11612.903 | H49: =_xlfn.XLOOKUP(A49,'Salary Structure'!A:A,'Salary Structure'!D:D,"NOT FOUND")*E49/C49 -> 2903.2258 | I49: =_xlfn.XLOOKUP(A49,'Salary Structure'!A:A,'Salary Structure'!E:E,"NOT FOUND")*E49/C49 -> 4838.7097 | J49: 0 | K49: =ROUND(F49*E49/C49,0) -> 29032 | L49: =SUM(G49:K49) -> 48386.839 | M49: =F49*12/100 -> 3600 | N49: =L49*75/10000 -> 362.90129 | O49: 208 | P49: =L49*3/100 -> 1451.6052 | Q49: 0 | S49: =M49+N49+O49+P49+Q49 -> 5622.5065 | T49: =L49-S49 -> 42764.332
A50: EMP009 | B50: 46143 | C50: =DAY(EOMONTH(B50,0)) -> 31 | D50: 2 | E50: =C50-D50 -> 29 | F50: =_xlfn.XLOOKUP(A50,'Salary Structure'!A:A,'Salary Structure'!B:B,"NOT FOUND") -> 23000 | G50: =_xlfn.XLOOKUP(A50,'Salary Structure'!A:A,'Salary Structure'!C:C,"NOT FOUND")*E50/C50 -> 8606.4516 | H50: =_xlfn.XLOOKUP(A50,'Salary Structure'!A:A,'Salary Structure'!D:D,"NOT FOUND")*E50/C50 -> 2151.6129 | I50: =_xlfn.XLOOKUP(A50,'Salary Structure'!A:A,'Salary Structure'!E:E,"NOT FOUND")*E50/C50 -> 3274.1935 | J50: 0 | K50: =ROUND(F50*E50/C50,0) -> 21516 | L50: =SUM(G50:K50) -> 35548.258 | M50: =F50*12/100 -> 2760 | N50: =L50*75/10000 -> 266.61194 | O50: 208 | P50: =L50*3/100 -> 1066.4477 | Q50: 0 | S50: =M50+N50+O50+P50+Q50 -> 4301.0597 | T50: =L50-S50 -> 31247.198
A51: EMP010 | B51: 46143 | C51: =DAY(EOMONTH(B51,0)) -> 31 | D51: 4 | E51: =C51-D51 -> 27 | F51: =_xlfn.XLOOKUP(A51,'Salary Structure'!A:A,'Salary Structure'!B:B,"NOT FOUND") -> 45000 | G51: =_xlfn.XLOOKUP(A51,'Salary Structure'!A:A,'Salary Structure'!C:C,"NOT FOUND")*E51/C51 -> 15677.419 | H51: =_xlfn.XLOOKUP(A51,'Salary Structure'!A:A,'Salary Structure'!D:D,"NOT FOUND")*E51/C51 -> 3919.3548 | I51: =_xlfn.XLOOKUP(A51,'Salary Structure'!A:A,'Salary Structure'!E:E,"NOT FOUND")*E51/C51 -> 6967.7419 | J51: 0 | K51: =ROUND(F51*E51/C51,0) -> 39194 | L51: =SUM(G51:K51) -> 65758.516 | M51: =F51*12/100 -> 5400 | N51: =L51*75/10000 -> 493.18887 | O51: 208 | P51: =L51*3/100 -> 1972.7555 | Q51: 500 | R51: Loan/Advance EMI recovery | S51: =M51+N51+O51+P51+Q51 -> 8573.9444 | T51: =L51-S51 -> 57184.572
A52: EMP001 | B52: 46174 | C52: =DAY(EOMONTH(B52,0)) -> 30 | D52: 0 | E52: =C52-D52 -> 30 | F52: =_xlfn.XLOOKUP(A52,'Salary Structure'!A:A,'Salary Structure'!B:B,"NOT FOUND") -> 30000 | G52: =_xlfn.XLOOKUP(A52,'Salary Structure'!A:A,'Salary Structure'!C:C,"NOT FOUND")*E52/C52 -> 12000 | H52: =_xlfn.XLOOKUP(A52,'Salary Structure'!A:A,'Salary Structure'!D:D,"NOT FOUND")*E52/C52 -> 3000 | I52: =_xlfn.XLOOKUP(A52,'Salary Structure'!A:A,'Salary Structure'!E:E,"NOT FOUND")*E52/C52 -> 5000 | J52: 0 | K52: =ROUND(F52*E52/C52,0) -> 30000 | L52: =SUM(G52:K52) -> 50000 | M52: =F52*12/100 -> 3600 | N52: =L52*75/10000 -> 375 | O52: 208 | P52: =L52*3/100 -> 1500 | Q52: 0 | S52: =M52+N52+O52+P52+Q52 -> 5683 | T52: =L52-S52 -> 44317
A53: EMP002 | B53: 46174 | C53: =DAY(EOMONTH(B53,0)) -> 30 | D53: 0 | E53: =C53-D53 -> 30 | F53: =_xlfn.XLOOKUP(A53,'Salary Structure'!A:A,'Salary Structure'!B:B,"NOT FOUND") -> 25000 | G53: =_xlfn.XLOOKUP(A53,'Salary Structure'!A:A,'Salary Structure'!C:C,"NOT FOUND")*E53/C53 -> 10000 | H53: =_xlfn.XLOOKUP(A53,'Salary Structure'!A:A,'Salary Structure'!D:D,"NOT FOUND")*E53/C53 -> 2500 | I53: =_xlfn.XLOOKUP(A53,'Salary Structure'!A:A,'Salary Structure'!E:E,"NOT FOUND")*E53/C53 -> 4000 | J53: 0 | K53: =ROUND(F53*E53/C53,0) -> 25000 | L53: =SUM(G53:K53) -> 41500 | M53: =F53*12/100 -> 3000 | N53: =L53*75/10000 -> 311.25 | O53: 208 | P53: =L53*3/100 -> 1245 | Q53: 0 | S53: =M53+N53+O53+P53+Q53 -> 4764.25 | T53: =L53-S53 -> 36735.75
A54: EMP003 | B54: 46174 | C54: =DAY(EOMONTH(B54,0)) -> 30 | D54: 1 | E54: =C54-D54 -> 29 | F54: =_xlfn.XLOOKUP(A54,'Salary Structure'!A:A,'Salary Structure'!B:B,"NOT FOUND") -> 28000 | G54: =_xlfn.XLOOKUP(A54,'Salary Structure'!A:A,'Salary Structure'!C:C,"NOT FOUND")*E54/C54 -> 10826.667 | H54: =_xlfn.XLOOKUP(A54,'Salary Structure'!A:A,'Salary Structure'!D:D,"NOT FOUND")*E54/C54 -> 2706.6667 | I54: =_xlfn.XLOOKUP(A54,'Salary Structure'!A:A,'Salary Structure'!E:E,"NOT FOUND")*E54/C54 -> 4350 | J54: 0 | K54: =ROUND(F54*E54/C54,0) -> 27067 | L54: =SUM(G54:K54) -> 44950.333 | M54: =F54*12/100 -> 3360 | N54: =L54*75/10000 -> 337.1275 | O54: 208 | P54: =L54*3/100 -> 1348.51 | Q54: 300 | R54: Loan/Advance EMI recovery | S54: =M54+N54+O54+P54+Q54 -> 5553.6375 | T54: =L54-S54 -> 39396.696
A55: EMP004 | B55: 46174 | C55: =DAY(EOMONTH(B55,0)) -> 30 | D55: 1 | E55: =C55-D55 -> 29 | F55: =_xlfn.XLOOKUP(A55,'Salary Structure'!A:A,'Salary Structure'!B:B,"NOT FOUND") -> 26000 | G55: =_xlfn.XLOOKUP(A55,'Salary Structure'!A:A,'Salary Structure'!C:C,"NOT FOUND")*E55/C55 -> 10053.333 | H55: =_xlfn.XLOOKUP(A55,'Salary Structure'!A:A,'Salary Structure'!D:D,"NOT FOUND")*E55/C55 -> 2513.3333 | I55: =_xlfn.XLOOKUP(A55,'Salary Structure'!A:A,'Salary Structure'!E:E,"NOT FOUND")*E55/C55 -> 3866.6667 | J55: 0 | K55: =ROUND(F55*E55/C55,0) -> 25133 | L55: =SUM(G55:K55) -> 41566.333 | M55: =F55*12/100 -> 3120 | N55: =L55*75/10000 -> 311.7475 | O55: 208 | P55: =L55*3/100 -> 1246.99 | Q55: 0 | S55: =M55+N55+O55+P55+Q55 -> 4886.7375 | T55: =L55-S55 -> 36679.596
A56: EMP005 | B56: 46174 | C56: =DAY(EOMONTH(B56,0)) -> 30 | D56: 2 | E56: =C56-D56 -> 28 | F56: =_xlfn.XLOOKUP(A56,'Salary Structure'!A:A,'Salary Structure'!B:B,"NOT FOUND") -> 32000 | G56: =_xlfn.XLOOKUP(A56,'Salary Structure'!A:A,'Salary Structure'!C:C,"NOT FOUND")*E56/C56 -> 11946.667 | H56: =_xlfn.XLOOKUP(A56,'Salary Structure'!A:A,'Salary Structure'!D:D,"NOT FOUND")*E56/C56 -> 2986.6667 | I56: =_xlfn.XLOOKUP(A56,'Salary Structure'!A:A,'Salary Structure'!E:E,"NOT FOUND")*E56/C56 -> 5133.3333 | J56: 0 | K56: =ROUND(F56*E56/C56,0) -> 29867 | L56: =SUM(G56:K56) -> 49933.667 | M56: =F56*12/100 -> 3840 | N56: =L56*75/10000 -> 374.5025 | O56: 208 | P56: =L56*3/100 -> 1498.01 | Q56: 0 | S56: =M56+N56+O56+P56+Q56 -> 5920.5125 | T56: =L56-S56 -> 44013.154
A57: EMP006 | B57: 46174 | C57: =DAY(EOMONTH(B57,0)) -> 30 | D57: 0 | E57: =C57-D57 -> 30 | F57: =_xlfn.XLOOKUP(A57,'Salary Structure'!A:A,'Salary Structure'!B:B,"NOT FOUND") -> 24000 | G57: =_xlfn.XLOOKUP(A57,'Salary Structure'!A:A,'Salary Structure'!C:C,"NOT FOUND")*E57/C57 -> 9600 | H57: =_xlfn.XLOOKUP(A57,'Salary Structure'!A:A,'Salary Structure'!D:D,"NOT FOUND")*E57/C57 -> 2400 | I57: =_xlfn.XLOOKUP(A57,'Salary Structure'!A:A,'Salary Structure'!E:E,"NOT FOUND")*E57/C57 -> 3500 | J57: 0 | K57: =ROUND(F57*E57/C57,0) -> 24000 | L57: =SUM(G57:K57) -> 39500 | M57: =F57*12/100 -> 2880 | N57: =L57*75/10000 -> 296.25 | O57: 208 | P57: =L57*3/100 -> 1185 | Q57: 0 | S57: =M57+N57+O57+P57+Q57 -> 4569.25 | T57: =L57-S57 -> 34930.75
A58: EMP007 | B58: 46174 | C58: =DAY(EOMONTH(B58,0)) -> 30 | D58: 1 | E58: =C58-D58 -> 29 | F58: =_xlfn.XLOOKUP(A58,'Salary Structure'!A:A,'Salary Structure'!B:B,"NOT FOUND") -> 40000 | G58: =_xlfn.XLOOKUP(A58,'Salary Structure'!A:A,'Salary Structure'!C:C,"NOT FOUND")*E58/C58 -> 15466.667 | H58: =_xlfn.XLOOKUP(A58,'Salary Structure'!A:A,'Salary Structure'!D:D,"NOT FOUND")*E58/C58 -> 3866.6667 | I58: =_xlfn.XLOOKUP(A58,'Salary Structure'!A:A,'Salary Structure'!E:E,"NOT FOUND")*E58/C58 -> 6766.6667 | J58: 0 | K58: =ROUND(F58*E58/C58,0) -> 38667 | L58: =SUM(G58:K58) -> 64767 | M58: =F58*12/100 -> 4800 | N58: =L58*75/10000 -> 485.7525 | O58: 208 | P58: =L58*3/100 -> 1943.01 | Q58: 0 | S58: =M58+N58+O58+P58+Q58 -> 7436.7625 | T58: =L58-S58 -> 57330.238
A59: EMP008 | B59: 46174 | C59: =DAY(EOMONTH(B59,0)) -> 30 | D59: 0 | E59: =C59-D59 -> 30 | F59: =_xlfn.XLOOKUP(A59,'Salary Structure'!A:A,'Salary Structure'!B:B,"NOT FOUND") -> 30000 | G59: =_xlfn.XLOOKUP(A59,'Salary Structure'!A:A,'Salary Structure'!C:C,"NOT FOUND")*E59/C59 -> 12000 | H59: =_xlfn.XLOOKUP(A59,'Salary Structure'!A:A,'Salary Structure'!D:D,"NOT FOUND")*E59/C59 -> 3000 | I59: =_xlfn.XLOOKUP(A59,'Salary Structure'!A:A,'Salary Structure'!E:E,"NOT FOUND")*E59/C59 -> 5000 | J59: 0 | K59: =ROUND(F59*E59/C59,0) -> 30000 | L59: =SUM(G59:K59) -> 50000 | M59: =F59*12/100 -> 3600 | N59: =L59*75/10000 -> 375 | O59: 208 | P59: =L59*3/100 -> 1500 | Q59: 0 | S59: =M59+N59+O59+P59+Q59 -> 5683 | T59: =L59-S59 -> 44317
A60: EMP009 | B60: 46174 | C60: =DAY(EOMONTH(B60,0)) -> 30 | D60: 0 | E60: =C60-D60 -> 30 | F60: =_xlfn.XLOOKUP(A60,'Salary Structure'!A:A,'Salary Structure'!B:B,"NOT FOUND") -> 23000 | G60: =_xlfn.XLOOKUP(A60,'Salary Structure'!A:A,'Salary Structure'!C:C,"NOT FOUND")*E60/C60 -> 9200 | H60: =_xlfn.XLOOKUP(A60,'Salary Structure'!A:A,'Salary Structure'!D:D,"NOT FOUND")*E60/C60 -> 2300 | I60: =_xlfn.XLOOKUP(A60,'Salary Structure'!A:A,'Salary Structure'!E:E,"NOT FOUND")*E60/C60 -> 3500 | J60: 0 | K60: =ROUND(F60*E60/C60,0) -> 23000 | L60: =SUM(G60:K60) -> 38000 | M60: =F60*12/100 -> 2760 | N60: =L60*75/10000 -> 285 | O60: 208 | P60: =L60*3/100 -> 1140 | Q60: 0 | S60: =M60+N60+O60+P60+Q60 -> 4393 | T60: =L60-S60 -> 33607
A61: EMP010 | B61: 46174 | C61: =DAY(EOMONTH(B61,0)) -> 30 | D61: 1 | E61: =C61-D61 -> 29 | F61: =_xlfn.XLOOKUP(A61,'Salary Structure'!A:A,'Salary Structure'!B:B,"NOT FOUND") -> 45000 | G61: =_xlfn.XLOOKUP(A61,'Salary Structure'!A:A,'Salary Structure'!C:C,"NOT FOUND")*E61/C61 -> 17400 | H61: =_xlfn.XLOOKUP(A61,'Salary Structure'!A:A,'Salary Structure'!D:D,"NOT FOUND")*E61/C61 -> 4350 | I61: =_xlfn.XLOOKUP(A61,'Salary Structure'!A:A,'Salary Structure'!E:E,"NOT FOUND")*E61/C61 -> 7733.3333 | J61: 0 | K61: =ROUND(F61*E61/C61,0) -> 43500 | L61: =SUM(G61:K61) -> 72983.333 | M61: =F61*12/100 -> 5400 | N61: =L61*75/10000 -> 547.375 | O61: 208 | P61: =L61*3/100 -> 2189.5 | Q61: 500 | R61: Loan/Advance EMI recovery | S61: =M61+N61+O61+P61+Q61 -> 8844.875 | T61: =L61-S61 -> 64138.458
A62: EMP001 | B62: 46204 | C62: =DAY(EOMONTH(B62,0)) -> 31 | D62: 1 | E62: =C62-D62 -> 30 | F62: =_xlfn.XLOOKUP(A62,'Salary Structure'!A:A,'Salary Structure'!B:B,"NOT FOUND") -> 30000 | G62: =_xlfn.XLOOKUP(A62,'Salary Structure'!A:A,'Salary Structure'!C:C,"NOT FOUND")*E62/C62 -> 11612.903 | H62: =_xlfn.XLOOKUP(A62,'Salary Structure'!A:A,'Salary Structure'!D:D,"NOT FOUND")*E62/C62 -> 2903.2258 | I62: =_xlfn.XLOOKUP(A62,'Salary Structure'!A:A,'Salary Structure'!E:E,"NOT FOUND")*E62/C62 -> 4838.7097 | J62: 0 | K62: =ROUND(F62*E62/C62,0) -> 29032 | L62: =SUM(G62:K62) -> 48386.839 | M62: =F62*12/100 -> 3600 | N62: =L62*75/10000 -> 362.90129 | O62: 208 | P62: =L62*3/100 -> 1451.6052 | Q62: 0 | S62: =M62+N62+O62+P62+Q62 -> 5622.5065 | T62: =L62-S62 -> 42764.332
A63: EMP002 | B63: 46204 | C63: =DAY(EOMONTH(B63,0)) -> 31 | D63: 2 | E63: =C63-D63 -> 29 | F63: =_xlfn.XLOOKUP(A63,'Salary Structure'!A:A,'Salary Structure'!B:B,"NOT FOUND") -> 25000 | G63: =_xlfn.XLOOKUP(A63,'Salary Structure'!A:A,'Salary Structure'!C:C,"NOT FOUND")*E63/C63 -> 9354.8387 | H63: =_xlfn.XLOOKUP(A63,'Salary Structure'!A:A,'Salary Structure'!D:D,"NOT FOUND")*E63/C63 -> 2338.7097 | I63: =_xlfn.XLOOKUP(A63,'Salary Structure'!A:A,'Salary Structure'!E:E,"NOT FOUND")*E63/C63 -> 3741.9355 | J63: 0 | K63: =ROUND(F63*E63/C63,0) -> 23387 | L63: =SUM(G63:K63) -> 38822.484 | M63: =F63*12/100 -> 3000 | N63: =L63*75/10000 -> 291.16863 | O63: 208 | P63: =L63*3/100 -> 1164.6745 | Q63: 0 | S63: =M63+N63+O63+P63+Q63 -> 4663.8431 | T63: =L63-S63 -> 34158.641
A64: EMP003 | B64: 46204 | C64: =DAY(EOMONTH(B64,0)) -> 31 | D64: 0 | E64: =C64-D64 -> 31 | F64: =_xlfn.XLOOKUP(A64,'Salary Structure'!A:A,'Salary Structure'!B:B,"NOT FOUND") -> 28000 | G64: =_xlfn.XLOOKUP(A64,'Salary Structure'!A:A,'Salary Structure'!C:C,"NOT FOUND")*E64/C64 -> 11200 | H64: =_xlfn.XLOOKUP(A64,'Salary Structure'!A:A,'Salary Structure'!D:D,"NOT FOUND")*E64/C64 -> 2800 | I64: =_xlfn.XLOOKUP(A64,'Salary Structure'!A:A,'Salary Structure'!E:E,"NOT FOUND")*E64/C64 -> 4500 | J64: 0 | K64: =ROUND(F64*E64/C64,0) -> 28000 | L64: =SUM(G64:K64) -> 46500 | M64: =F64*12/100 -> 3360 | N64: =L64*75/10000 -> 348.75 | O64: 208 | P64: =L64*3/100 -> 1395 | Q64: 300 | R64: Loan/Advance EMI recovery | S64: =M64+N64+O64+P64+Q64 -> 5611.75 | T64: =L64-S64 -> 40888.25
A65: EMP004 | B65: 46204 | C65: =DAY(EOMONTH(B65,0)) -> 31 | D65: 1 | E65: =C65-D65 -> 30 | F65: =_xlfn.XLOOKUP(A65,'Salary Structure'!A:A,'Salary Structure'!B:B,"NOT FOUND") -> 26000 | G65: =_xlfn.XLOOKUP(A65,'Salary Structure'!A:A,'Salary Structure'!C:C,"NOT FOUND")*E65/C65 -> 10064.516 | H65: =_xlfn.XLOOKUP(A65,'Salary Structure'!A:A,'Salary Structure'!D:D,"NOT FOUND")*E65/C65 -> 2516.129 | I65: =_xlfn.XLOOKUP(A65,'Salary Structure'!A:A,'Salary Structure'!E:E,"NOT FOUND")*E65/C65 -> 3870.9677 | J65: 0 | K65: =ROUND(F65*E65/C65,0) -> 25161 | L65: =SUM(G65:K65) -> 41612.613 | M65: =F65*12/100 -> 3120 | N65: =L65*75/10000 -> 312.0946 | O65: 208 | P65: =L65*3/100 -> 1248.3784 | Q65: 0 | S65: =M65+N65+O65+P65+Q65 -> 4888.473 | T65: =L65-S65 -> 36724.14
A66: EMP005 | B66: 46204 | C66: =DAY(EOMONTH(B66,0)) -> 31 | D66: 0 | E66: =C66-D66 -> 31 | F66: =_xlfn.XLOOKUP(A66,'Salary Structure'!A:A,'Salary Structure'!B:B,"NOT FOUND") -> 32000 | G66: =_xlfn.XLOOKUP(A66,'Salary Structure'!A:A,'Salary Structure'!C:C,"NOT FOUND")*E66/C66 -> 12800 | H66: =_xlfn.XLOOKUP(A66,'Salary Structure'!A:A,'Salary Structure'!D:D,"NOT FOUND")*E66/C66 -> 3200 | I66: =_xlfn.XLOOKUP(A66,'Salary Structure'!A:A,'Salary Structure'!E:E,"NOT FOUND")*E66/C66 -> 5500 | J66: 0 | K66: =ROUND(F66*E66/C66,0) -> 32000 | L66: =SUM(G66:K66) -> 53500 | M66: =F66*12/100 -> 3840 | N66: =L66*75/10000 -> 401.25 | O66: 208 | P66: =L66*3/100 -> 1605 | Q66: 0 | S66: =M66+N66+O66+P66+Q66 -> 6054.25 | T66: =L66-S66 -> 47445.75
A67: EMP006 | B67: 46204 | C67: =DAY(EOMONTH(B67,0)) -> 31 | D67: 2 | E67: =C67-D67 -> 29 | F67: =_xlfn.XLOOKUP(A67,'Salary Structure'!A:A,'Salary Structure'!B:B,"NOT FOUND") -> 24000 | G67: =_xlfn.XLOOKUP(A67,'Salary Structure'!A:A,'Salary Structure'!C:C,"NOT FOUND")*E67/C67 -> 8980.6452 | H67: =_xlfn.XLOOKUP(A67,'Salary Structure'!A:A,'Salary Structure'!D:D,"NOT FOUND")*E67/C67 -> 2245.1613 | I67: =_xlfn.XLOOKUP(A67,'Salary Structure'!A:A,'Salary Structure'!E:E,"NOT FOUND")*E67/C67 -> 3274.1935 | J67: 0 | K67: =ROUND(F67*E67/C67,0) -> 22452 | L67: =SUM(G67:K67) -> 36952 | M67: =F67*12/100 -> 2880 | N67: =L67*75/10000 -> 277.14 | O67: 208 | P67: =L67*3/100 -> 1108.56 | Q67: 0 | S67: =M67+N67+O67+P67+Q67 -> 4473.7 | T67: =L67-S67 -> 32478.3
A68: EMP007 | B68: 46204 | C68: =DAY(EOMONTH(B68,0)) -> 31 | D68: 3 | E68: =C68-D68 -> 28 | F68: =_xlfn.XLOOKUP(A68,'Salary Structure'!A:A,'Salary Structure'!B:B,"NOT FOUND") -> 40000 | G68: =_xlfn.XLOOKUP(A68,'Salary Structure'!A:A,'Salary Structure'!C:C,"NOT FOUND")*E68/C68 -> 14451.613 | H68: =_xlfn.XLOOKUP(A68,'Salary Structure'!A:A,'Salary Structure'!D:D,"NOT FOUND")*E68/C68 -> 3612.9032 | I68: =_xlfn.XLOOKUP(A68,'Salary Structure'!A:A,'Salary Structure'!E:E,"NOT FOUND")*E68/C68 -> 6322.5806 | J68: 0 | K68: =ROUND(F68*E68/C68,0) -> 36129 | L68: =SUM(G68:K68) -> 60516.097 | M68: =F68*12/100 -> 4800 | N68: =L68*75/10000 -> 453.87073 | O68: 208 | P68: =L68*3/100 -> 1815.4829 | Q68: 0 | S68: =M68+N68+O68+P68+Q68 -> 7277.3536 | T68: =L68-S68 -> 53238.743
A69: EMP008 | B69: 46204 | C69: =DAY(EOMONTH(B69,0)) -> 31 | D69: 1 | E69: =C69-D69 -> 30 | F69: =_xlfn.XLOOKUP(A69,'Salary Structure'!A:A,'Salary Structure'!B:B,"NOT FOUND") -> 30000 | G69: =_xlfn.XLOOKUP(A69,'Salary Structure'!A:A,'Salary Structure'!C:C,"NOT FOUND")*E69/C69 -> 11612.903 | H69: =_xlfn.XLOOKUP(A69,'Salary Structure'!A:A,'Salary Structure'!D:D,"NOT FOUND")*E69/C69 -> 2903.2258 | I69: =_xlfn.XLOOKUP(A69,'Salary Structure'!A:A,'Salary Structure'!E:E,"NOT FOUND")*E69/C69 -> 4838.7097 | J69: 0 | K69: =ROUND(F69*E69/C69,0) -> 29032 | L69: =SUM(G69:K69) -> 48386.839 | M69: =F69*12/100 -> 3600 | N69: =L69*75/10000 -> 362.90129 | O69: 208 | P69: =L69*3/100 -> 1451.6052 | Q69: 0 | S69: =M69+N69+O69+P69+Q69 -> 5622.5065 | T69: =L69-S69 -> 42764.332
A70: EMP009 | B70: 46204 | C70: =DAY(EOMONTH(B70,0)) -> 31 | D70: 0 | E70: =C70-D70 -> 31 | F70: =_xlfn.XLOOKUP(A70,'Salary Structure'!A:A,'Salary Structure'!B:B,"NOT FOUND") -> 23000 | G70: =_xlfn.XLOOKUP(A70,'Salary Structure'!A:A,'Salary Structure'!C:C,"NOT FOUND")*E70/C70 -> 9200 | H70: =_xlfn.XLOOKUP(A70,'Salary Structure'!A:A,'Salary Structure'!D:D,"NOT FOUND")*E70/C70 -> 2300 | I70: =_xlfn.XLOOKUP(A70,'Salary Structure'!A:A,'Salary Structure'!E:E,"NOT FOUND")*E70/C70 -> 3500 | J70: 0 | K70: =ROUND(F70*E70/C70,0) -> 23000 | L70: =SUM(G70:K70) -> 38000 | M70: =F70*12/100 -> 2760 | N70: =L70*75/10000 -> 285 | O70: 208 | P70: =L70*3/100 -> 1140 | Q70: 0 | S70: =M70+N70+O70+P70+Q70 -> 4393 | T70: =L70-S70 -> 33607
A71: EMP010 | B71: 46204 | C71: =DAY(EOMONTH(B71,0)) -> 31 | D71: 3 | E71: =C71-D71 -> 28 | F71: =_xlfn.XLOOKUP(A71,'Salary Structure'!A:A,'Salary Structure'!B:B,"NOT FOUND") -> 45000 | G71: =_xlfn.XLOOKUP(A71,'Salary Structure'!A:A,'Salary Structure'!C:C,"NOT FOUND")*E71/C71 -> 16258.065 | H71: =_xlfn.XLOOKUP(A71,'Salary Structure'!A:A,'Salary Structure'!D:D,"NOT FOUND")*E71/C71 -> 4064.5161 | I71: =_xlfn.XLOOKUP(A71,'Salary Structure'!A:A,'Salary Structure'!E:E,"NOT FOUND")*E71/C71 -> 7225.8065 | J71: 0 | K71: =ROUND(F71*E71/C71,0) -> 40645 | L71: =SUM(G71:K71) -> 68193.387 | M71: =F71*12/100 -> 5400 | N71: =L71*75/10000 -> 511.4504 | O71: 208 | P71: =L71*3/100 -> 2045.8016 | Q71: 500 | R71: Loan/Advance EMI recovery | S71: =M71+N71+O71+P71+Q71 -> 8665.252 | T71: =L71-S71 -> 59528.135
A72: EMP001 | B72: 46235 | C72: =DAY(EOMONTH(B72,0)) -> 31 | D72: 0 | E72: =C72-D72 -> 31 | F72: =_xlfn.XLOOKUP(A72,'Salary Structure'!A:A,'Salary Structure'!B:B,"NOT FOUND") -> 30000 | G72: =_xlfn.XLOOKUP(A72,'Salary Structure'!A:A,'Salary Structure'!C:C,"NOT FOUND")*E72/C72 -> 12000 | H72: =_xlfn.XLOOKUP(A72,'Salary Structure'!A:A,'Salary Structure'!D:D,"NOT FOUND")*E72/C72 -> 3000 | I72: =_xlfn.XLOOKUP(A72,'Salary Structure'!A:A,'Salary Structure'!E:E,"NOT FOUND")*E72/C72 -> 5000 | J72: 0 | K72: =ROUND(F72*E72/C72,0) -> 30000 | L72: =SUM(G72:K72) -> 50000 | M72: =F72*12/100 -> 3600 | N72: =L72*75/10000 -> 375 | O72: 208 | P72: =L72*3/100 -> 1500 | Q72: 0 | S72: =M72+N72+O72+P72+Q72 -> 5683 | T72: =L72-S72 -> 44317
A73: EMP002 | B73: 46235 | C73: =DAY(EOMONTH(B73,0)) -> 31 | D73: 0 | E73: =C73-D73 -> 31 | F73: =_xlfn.XLOOKUP(A73,'Salary Structure'!A:A,'Salary Structure'!B:B,"NOT FOUND") -> 25000 | G73: =_xlfn.XLOOKUP(A73,'Salary Structure'!A:A,'Salary Structure'!C:C,"NOT FOUND")*E73/C73 -> 10000 | H73: =_xlfn.XLOOKUP(A73,'Salary Structure'!A:A,'Salary Structure'!D:D,"NOT FOUND")*E73/C73 -> 2500 | I73: =_xlfn.XLOOKUP(A73,'Salary Structure'!A:A,'Salary Structure'!E:E,"NOT FOUND")*E73/C73 -> 4000 | J73: 0 | K73: =ROUND(F73*E73/C73,0) -> 25000 | L73: =SUM(G73:K73) -> 41500 | M73: =F73*12/100 -> 3000 | N73: =L73*75/10000 -> 311.25 | O73: 208 | P73: =L73*3/100 -> 1245 | Q73: 0 | S73: =M73+N73+O73+P73+Q73 -> 4764.25 | T73: =L73-S73 -> 36735.75
A74: EMP003 | B74: 46235 | C74: =DAY(EOMONTH(B74,0)) -> 31 | D74: 0 | E74: =C74-D74 -> 31 | F74: =_xlfn.XLOOKUP(A74,'Salary Structure'!A:A,'Salary Structure'!B:B,"NOT FOUND") -> 28000 | G74: =_xlfn.XLOOKUP(A74,'Salary Structure'!A:A,'Salary Structure'!C:C,"NOT FOUND")*E74/C74 -> 11200 | H74: =_xlfn.XLOOKUP(A74,'Salary Structure'!A:A,'Salary Structure'!D:D,"NOT FOUND")*E74/C74 -> 2800 | I74: =_xlfn.XLOOKUP(A74,'Salary Structure'!A:A,'Salary Structure'!E:E,"NOT FOUND")*E74/C74 -> 4500 | J74: 0 | K74: =ROUND(F74*E74/C74,0) -> 28000 | L74: =SUM(G74:K74) -> 46500 | M74: =F74*12/100 -> 3360 | N74: =L74*75/10000 -> 348.75 | O74: 208 | P74: =L74*3/100 -> 1395 | Q74: 300 | R74: Loan/Advance EMI recovery | S74: =M74+N74+O74+P74+Q74 -> 5611.75 | T74: =L74-S74 -> 40888.25
A75: EMP004 | B75: 46235 | C75: =DAY(EOMONTH(B75,0)) -> 31 | D75: 0 | E75: =C75-D75 -> 31 | F75: =_xlfn.XLOOKUP(A75,'Salary Structure'!A:A,'Salary Structure'!B:B,"NOT FOUND") -> 26000 | G75: =_xlfn.XLOOKUP(A75,'Salary Structure'!A:A,'Salary Structure'!C:C,"NOT FOUND")*E75/C75 -> 10400 | H75: =_xlfn.XLOOKUP(A75,'Salary Structure'!A:A,'Salary Structure'!D:D,"NOT FOUND")*E75/C75 -> 2600 | I75: =_xlfn.XLOOKUP(A75,'Salary Structure'!A:A,'Salary Structure'!E:E,"NOT FOUND")*E75/C75 -> 4000 | J75: 0 | K75: =ROUND(F75*E75/C75,0) -> 26000 | L75: =SUM(G75:K75) -> 43000 | M75: =F75*12/100 -> 3120 | N75: =L75*75/10000 -> 322.5 | O75: 208 | P75: =L75*3/100 -> 1290 | Q75: 0 | S75: =M75+N75+O75+P75+Q75 -> 4940.5 | T75: =L75-S75 -> 38059.5
A76: EMP005 | B76: 46235 | C76: =DAY(EOMONTH(B76,0)) -> 31 | D76: 0 | E76: =C76-D76 -> 31 | F76: =_xlfn.XLOOKUP(A76,'Salary Structure'!A:A,'Salary Structure'!B:B,"NOT FOUND") -> 32000 | G76: =_xlfn.XLOOKUP(A76,'Salary Structure'!A:A,'Salary Structure'!C:C,"NOT FOUND")*E76/C76 -> 12800 | H76: =_xlfn.XLOOKUP(A76,'Salary Structure'!A:A,'Salary Structure'!D:D,"NOT FOUND")*E76/C76 -> 3200 | I76: =_xlfn.XLOOKUP(A76,'Salary Structure'!A:A,'Salary Structure'!E:E,"NOT FOUND")*E76/C76 -> 5500 | J76: 0 | K76: =ROUND(F76*E76/C76,0) -> 32000 | L76: =SUM(G76:K76) -> 53500 | M76: =F76*12/100 -> 3840 | N76: =L76*75/10000 -> 401.25 | O76: 208 | P76: =L76*3/100 -> 1605 | Q76: 0 | S76: =M76+N76+O76+P76+Q76 -> 6054.25 | T76: =L76-S76 -> 47445.75
A77: EMP006 | B77: 46235 | C77: =DAY(EOMONTH(B77,0)) -> 31 | D77: 1 | E77: =C77-D77 -> 30 | F77: =_xlfn.XLOOKUP(A77,'Salary Structure'!A:A,'Salary Structure'!B:B,"NOT FOUND") -> 24000 | G77: =_xlfn.XLOOKUP(A77,'Salary Structure'!A:A,'Salary Structure'!C:C,"NOT FOUND")*E77/C77 -> 9290.3226 | H77: =_xlfn.XLOOKUP(A77,'Salary Structure'!A:A,'Salary Structure'!D:D,"NOT FOUND")*E77/C77 -> 2322.5806 | I77: =_xlfn.XLOOKUP(A77,'Salary Structure'!A:A,'Salary Structure'!E:E,"NOT FOUND")*E77/C77 -> 3387.0968 | J77: 0 | K77: =ROUND(F77*E77/C77,0) -> 23226 | L77: =SUM(G77:K77) -> 38226 | M77: =F77*12/100 -> 2880 | N77: =L77*75/10000 -> 286.695 | O77: 208 | P77: =L77*3/100 -> 1146.78 | Q77: 0 | S77: =M77+N77+O77+P77+Q77 -> 4521.475 | T77: =L77-S77 -> 33704.525
A78: EMP007 | B78: 46235 | C78: =DAY(EOMONTH(B78,0)) -> 31 | D78: 4 | E78: =C78-D78 -> 27 | F78: =_xlfn.XLOOKUP(A78,'Salary Structure'!A:A,'Salary Structure'!B:B,"NOT FOUND") -> 40000 | G78: =_xlfn.XLOOKUP(A78,'Salary Structure'!A:A,'Salary Structure'!C:C,"NOT FOUND")*E78/C78 -> 13935.484 | H78: =_xlfn.XLOOKUP(A78,'Salary Structure'!A:A,'Salary Structure'!D:D,"NOT FOUND")*E78/C78 -> 3483.871 | I78: =_xlfn.XLOOKUP(A78,'Salary Structure'!A:A,'Salary Structure'!E:E,"NOT FOUND")*E78/C78 -> 6096.7742 | J78: 3000 | K78: =ROUND(F78*E78/C78,0) -> 34839 | L78: =SUM(G78:K78) -> 61355.129 | M78: =F78*12/100 -> 4800 | N78: =L78*75/10000 -> 460.16347 | O78: 208 | P78: =L78*3/100 -> 1840.6539 | Q78: 0 | S78: =M78+N78+O78+P78+Q78 -> 7308.8173 | T78: =L78-S78 -> 54046.312
A79: EMP008 | B79: 46235 | C79: =DAY(EOMONTH(B79,0)) -> 31 | D79: 7 | E79: =C79-D79 -> 24 | F79: =_xlfn.XLOOKUP(A79,'Salary Structure'!A:A,'Salary Structure'!B:B,"NOT FOUND") -> 30000 | G79: =_xlfn.XLOOKUP(A79,'Salary Structure'!A:A,'Salary Structure'!C:C,"NOT FOUND")*E79/C79 -> 9290.3226 | H79: =_xlfn.XLOOKUP(A79,'Salary Structure'!A:A,'Salary Structure'!D:D,"NOT FOUND")*E79/C79 -> 2322.5806 | I79: =_xlfn.XLOOKUP(A79,'Salary Structure'!A:A,'Salary Structure'!E:E,"NOT FOUND")*E79/C79 -> 3870.9677 | J79: 0 | K79: =ROUND(F79*E79/C79,0) -> 23226 | L79: =SUM(G79:K79) -> 38709.871 | M79: =F79*12/100 -> 3600 | N79: =L79*75/10000 -> 290.32403 | O79: 208 | P79: =L79*3/100 -> 1161.2961 | Q79: 0 | S79: =M79+N79+O79+P79+Q79 -> 5259.6202 | T79: =L79-S79 -> 33450.251
A80: EMP009 | B80: 46235 | C80: =DAY(EOMONTH(B80,0)) -> 31 | D80: 1 | E80: =C80-D80 -> 30 | F80: =_xlfn.XLOOKUP(A80,'Salary Structure'!A:A,'Salary Structure'!B:B,"NOT FOUND") -> 23000 | G80: =_xlfn.XLOOKUP(A80,'Salary Structure'!A:A,'Salary Structure'!C:C,"NOT FOUND")*E80/C80 -> 8903.2258 | H80: =_xlfn.XLOOKUP(A80,'Salary Structure'!A:A,'Salary Structure'!D:D,"NOT FOUND")*E80/C80 -> 2225.8065 | I80: =_xlfn.XLOOKUP(A80,'Salary Structure'!A:A,'Salary Structure'!E:E,"NOT FOUND")*E80/C80 -> 3387.0968 | J80: 0 | K80: =ROUND(F80*E80/C80,0) -> 22258 | L80: =SUM(G80:K80) -> 36774.129 | M80: =F80*12/100 -> 2760 | N80: =L80*75/10000 -> 275.80597 | O80: 208 | P80: =L80*3/100 -> 1103.2239 | Q80: 0 | S80: =M80+N80+O80+P80+Q80 -> 4347.0298 | T80: =L80-S80 -> 32427.099
A81: EMP010 | B81: 46235 | C81: =DAY(EOMONTH(B81,0)) -> 31 | D81: 0 | E81: =C81-D81 -> 31 | F81: =_xlfn.XLOOKUP(A81,'Salary Structure'!A:A,'Salary Structure'!B:B,"NOT FOUND") -> 45000 | G81: =_xlfn.XLOOKUP(A81,'Salary Structure'!A:A,'Salary Structure'!C:C,"NOT FOUND")*E81/C81 -> 18000 | H81: =_xlfn.XLOOKUP(A81,'Salary Structure'!A:A,'Salary Structure'!D:D,"NOT FOUND")*E81/C81 -> 4500 | I81: =_xlfn.XLOOKUP(A81,'Salary Structure'!A:A,'Salary Structure'!E:E,"NOT FOUND")*E81/C81 -> 8000 | J81: 0 | K81: =ROUND(F81*E81/C81,0) -> 45000 | L81: =SUM(G81:K81) -> 75500 | M81: =F81*12/100 -> 5400 | N81: =L81*75/10000 -> 566.25 | O81: 208 | P81: =L81*3/100 -> 2265 | Q81: 500 | R81: Loan/Advance EMI recovery | S81: =M81+N81+O81+P81+Q81 -> 8939.25 | T81: =L81-S81 -> 66560.75
A82: EMP001 | B82: 46266 | C82: =DAY(EOMONTH(B82,0)) -> 30 | D82: 0 | E82: =C82-D82 -> 30 | F82: =_xlfn.XLOOKUP(A82,'Salary Structure'!A:A,'Salary Structure'!B:B,"NOT FOUND") -> 30000 | G82: =_xlfn.XLOOKUP(A82,'Salary Structure'!A:A,'Salary Structure'!C:C,"NOT FOUND")*E82/C82 -> 12000 | H82: =_xlfn.XLOOKUP(A82,'Salary Structure'!A:A,'Salary Structure'!D:D,"NOT FOUND")*E82/C82 -> 3000 | I82: =_xlfn.XLOOKUP(A82,'Salary Structure'!A:A,'Salary Structure'!E:E,"NOT FOUND")*E82/C82 -> 5000 | J82: 0 | K82: =ROUND(F82*E82/C82,0) -> 30000 | L82: =SUM(G82:K82) -> 50000 | M82: =F82*12/100 -> 3600 | N82: =L82*75/10000 -> 375 | O82: 208 | P82: =L82*3/100 -> 1500 | Q82: 0 | S82: =M82+N82+O82+P82+Q82 -> 5683 | T82: =L82-S82 -> 44317
A83: EMP002 | B83: 46266 | C83: =DAY(EOMONTH(B83,0)) -> 30 | D83: 0 | E83: =C83-D83 -> 30 | F83: =_xlfn.XLOOKUP(A83,'Salary Structure'!A:A,'Salary Structure'!B:B,"NOT FOUND") -> 25000 | G83: =_xlfn.XLOOKUP(A83,'Salary Structure'!A:A,'Salary Structure'!C:C,"NOT FOUND")*E83/C83 -> 10000 | H83: =_xlfn.XLOOKUP(A83,'Salary Structure'!A:A,'Salary Structure'!D:D,"NOT FOUND")*E83/C83 -> 2500 | I83: =_xlfn.XLOOKUP(A83,'Salary Structure'!A:A,'Salary Structure'!E:E,"NOT FOUND")*E83/C83 -> 4000 | J83: 0 | K83: =ROUND(F83*E83/C83,0) -> 25000 | L83: =SUM(G83:K83) -> 41500 | M83: =F83*12/100 -> 3000 | N83: =L83*75/10000 -> 311.25 | O83: 208 | P83: =L83*3/100 -> 1245 | Q83: 0 | S83: =M83+N83+O83+P83+Q83 -> 4764.25 | T83: =L83-S83 -> 36735.75
A84: EMP003 | B84: 46266 | C84: =DAY(EOMONTH(B84,0)) -> 30 | D84: 0 | E84: =C84-D84 -> 30 | F84: =_xlfn.XLOOKUP(A84,'Salary Structure'!A:A,'Salary Structure'!B:B,"NOT FOUND") -> 28000 | G84: =_xlfn.XLOOKUP(A84,'Salary Structure'!A:A,'Salary Structure'!C:C,"NOT FOUND")*E84/C84 -> 11200 | H84: =_xlfn.XLOOKUP(A84,'Salary Structure'!A:A,'Salary Structure'!D:D,"NOT FOUND")*E84/C84 -> 2800 | I84: =_xlfn.XLOOKUP(A84,'Salary Structure'!A:A,'Salary Structure'!E:E,"NOT FOUND")*E84/C84 -> 4500 | J84: 0 | K84: =ROUND(F84*E84/C84,0) -> 28000 | L84: =SUM(G84:K84) -> 46500 | M84: =F84*12/100 -> 3360 | N84: =L84*75/10000 -> 348.75 | O84: 208 | P84: =L84*3/100 -> 1395 | Q84: 300 | R84: Loan/Advance EMI recovery | S84: =M84+N84+O84+P84+Q84 -> 5611.75 | T84: =L84-S84 -> 40888.25
A85: EMP004 | B85: 46266 | C85: =DAY(EOMONTH(B85,0)) -> 30 | D85: 1 | E85: =C85-D85 -> 29 | F85: =_xlfn.XLOOKUP(A85,'Salary Structure'!A:A,'Salary Structure'!B:B,"NOT FOUND") -> 26000 | G85: =_xlfn.XLOOKUP(A85,'Salary Structure'!A:A,'Salary Structure'!C:C,"NOT FOUND")*E85/C85 -> 10053.333 | H85: =_xlfn.XLOOKUP(A85,'Salary Structure'!A:A,'Salary Structure'!D:D,"NOT FOUND")*E85/C85 -> 2513.3333 | I85: =_xlfn.XLOOKUP(A85,'Salary Structure'!A:A,'Salary Structure'!E:E,"NOT FOUND")*E85/C85 -> 3866.6667 | J85: 0 | K85: =ROUND(F85*E85/C85,0) -> 25133 | L85: =SUM(G85:K85) -> 41566.333 | M85: =F85*12/100 -> 3120 | N85: =L85*75/10000 -> 311.7475 | O85: 208 | P85: =L85*3/100 -> 1246.99 | Q85: 0 | S85: =M85+N85+O85+P85+Q85 -> 4886.7375 | T85: =L85-S85 -> 36679.596
A86: EMP005 | B86: 46266 | C86: =DAY(EOMONTH(B86,0)) -> 30 | D86: 4 | E86: =C86-D86 -> 26 | F86: =_xlfn.XLOOKUP(A86,'Salary Structure'!A:A,'Salary Structure'!B:B,"NOT FOUND") -> 32000 | G86: =_xlfn.XLOOKUP(A86,'Salary Structure'!A:A,'Salary Structure'!C:C,"NOT FOUND")*E86/C86 -> 11093.333 | H86: =_xlfn.XLOOKUP(A86,'Salary Structure'!A:A,'Salary Structure'!D:D,"NOT FOUND")*E86/C86 -> 2773.3333 | I86: =_xlfn.XLOOKUP(A86,'Salary Structure'!A:A,'Salary Structure'!E:E,"NOT FOUND")*E86/C86 -> 4766.6667 | J86: 0 | K86: =ROUND(F86*E86/C86,0) -> 27733 | L86: =SUM(G86:K86) -> 46366.333 | M86: =F86*12/100 -> 3840 | N86: =L86*75/10000 -> 347.7475 | O86: 208 | P86: =L86*3/100 -> 1390.99 | Q86: 0 | S86: =M86+N86+O86+P86+Q86 -> 5786.7375 | T86: =L86-S86 -> 40579.596
A87: EMP006 | B87: 46266 | C87: =DAY(EOMONTH(B87,0)) -> 30 | D87: 2 | E87: =C87-D87 -> 28 | F87: =_xlfn.XLOOKUP(A87,'Salary Structure'!A:A,'Salary Structure'!B:B,"NOT FOUND") -> 24000 | G87: =_xlfn.XLOOKUP(A87,'Salary Structure'!A:A,'Salary Structure'!C:C,"NOT FOUND")*E87/C87 -> 8960 | H87: =_xlfn.XLOOKUP(A87,'Salary Structure'!A:A,'Salary Structure'!D:D,"NOT FOUND")*E87/C87 -> 2240 | I87: =_xlfn.XLOOKUP(A87,'Salary Structure'!A:A,'Salary Structure'!E:E,"NOT FOUND")*E87/C87 -> 3266.6667 | J87: 0 | K87: =ROUND(F87*E87/C87,0) -> 22400 | L87: =SUM(G87:K87) -> 36866.667 | M87: =F87*12/100 -> 2880 | N87: =L87*75/10000 -> 276.5 | O87: 208 | P87: =L87*3/100 -> 1106 | Q87: 0 | S87: =M87+N87+O87+P87+Q87 -> 4470.5 | T87: =L87-S87 -> 32396.167
A88: EMP007 | B88: 46266 | C88: =DAY(EOMONTH(B88,0)) -> 30 | D88: 1 | E88: =C88-D88 -> 29 | F88: =_xlfn.XLOOKUP(A88,'Salary Structure'!A:A,'Salary Structure'!B:B,"NOT FOUND") -> 40000 | G88: =_xlfn.XLOOKUP(A88,'Salary Structure'!A:A,'Salary Structure'!C:C,"NOT FOUND")*E88/C88 -> 15466.667 | H88: =_xlfn.XLOOKUP(A88,'Salary Structure'!A:A,'Salary Structure'!D:D,"NOT FOUND")*E88/C88 -> 3866.6667 | I88: =_xlfn.XLOOKUP(A88,'Salary Structure'!A:A,'Salary Structure'!E:E,"NOT FOUND")*E88/C88 -> 6766.6667 | J88: 0 | K88: =ROUND(F88*E88/C88,0) -> 38667 | L88: =SUM(G88:K88) -> 64767 | M88: =F88*12/100 -> 4800 | N88: =L88*75/10000 -> 485.7525 | O88: 208 | P88: =L88*3/100 -> 1943.01 | Q88: 0 | S88: =M88+N88+O88+P88+Q88 -> 7436.7625 | T88: =L88-S88 -> 57330.238
A89: EMP008 | B89: 46266 | C89: =DAY(EOMONTH(B89,0)) -> 30 | D89: 2 | E89: =C89-D89 -> 28 | F89: =_xlfn.XLOOKUP(A89,'Salary Structure'!A:A,'Salary Structure'!B:B,"NOT FOUND") -> 30000 | G89: =_xlfn.XLOOKUP(A89,'Salary Structure'!A:A,'Salary Structure'!C:C,"NOT FOUND")*E89/C89 -> 11200 | H89: =_xlfn.XLOOKUP(A89,'Salary Structure'!A:A,'Salary Structure'!D:D,"NOT FOUND")*E89/C89 -> 2800 | I89: =_xlfn.XLOOKUP(A89,'Salary Structure'!A:A,'Salary Structure'!E:E,"NOT FOUND")*E89/C89 -> 4666.6667 | J89: 0 | K89: =ROUND(F89*E89/C89,0) -> 28000 | L89: =SUM(G89:K89) -> 46666.667 | M89: =F89*12/100 -> 3600 | N89: =L89*75/10000 -> 350 | O89: 208 | P89: =L89*3/100 -> 1400 | Q89: 0 | S89: =M89+N89+O89+P89+Q89 -> 5558 | T89: =L89-S89 -> 41108.667
A90: EMP009 | B90: 46266 | C90: =DAY(EOMONTH(B90,0)) -> 30 | D90: 1 | E90: =C90-D90 -> 29 | F90: =_xlfn.XLOOKUP(A90,'Salary Structure'!A:A,'Salary Structure'!B:B,"NOT FOUND") -> 23000 | G90: =_xlfn.XLOOKUP(A90,'Salary Structure'!A:A,'Salary Structure'!C:C,"NOT FOUND")*E90/C90 -> 8893.3333 | H90: =_xlfn.XLOOKUP(A90,'Salary Structure'!A:A,'Salary Structure'!D:D,"NOT FOUND")*E90/C90 -> 2223.3333 | I90: =_xlfn.XLOOKUP(A90,'Salary Structure'!A:A,'Salary Structure'!E:E,"NOT FOUND")*E90/C90 -> 3383.3333 | J90: 0 | K90: =ROUND(F90*E90/C90,0) -> 22233 | L90: =SUM(G90:K90) -> 36733 | M90: =F90*12/100 -> 2760 | N90: =L90*75/10000 -> 275.4975 | O90: 208 | P90: =L90*3/100 -> 1101.99 | Q90: 0 | S90: =M90+N90+O90+P90+Q90 -> 4345.4875 | T90: =L90-S90 -> 32387.513
A91: EMP010 | B91: 46266 | C91: =DAY(EOMONTH(B91,0)) -> 30 | D91: 0 | E91: =C91-D91 -> 30 | F91: =_xlfn.XLOOKUP(A91,'Salary Structure'!A:A,'Salary Structure'!B:B,"NOT FOUND") -> 45000 | G91: =_xlfn.XLOOKUP(A91,'Salary Structure'!A:A,'Salary Structure'!C:C,"NOT FOUND")*E91/C91 -> 18000 | H91: =_xlfn.XLOOKUP(A91,'Salary Structure'!A:A,'Salary Structure'!D:D,"NOT FOUND")*E91/C91 -> 4500 | I91: =_xlfn.XLOOKUP(A91,'Salary Structure'!A:A,'Salary Structure'!E:E,"NOT FOUND")*E91/C91 -> 8000 | J91: 0 | K91: =ROUND(F91*E91/C91,0) -> 45000 | L91: =SUM(G91:K91) -> 75500 | M91: =F91*12/100 -> 5400 | N91: =L91*75/10000 -> 566.25 | O91: 208 | P91: =L91*3/100 -> 2265 | Q91: 500 | R91: Loan/Advance EMI recovery | S91: =M91+N91+O91+P91+Q91 -> 8939.25 | T91: =L91-S91 -> 66560.75
A92: EMP001 | B92: 46296 | C92: =DAY(EOMONTH(B92,0)) -> 31 | D92: 1 | E92: =C92-D92 -> 30 | F92: =_xlfn.XLOOKUP(A92,'Salary Structure'!A:A,'Salary Structure'!B:B,"NOT FOUND") -> 30000 | G92: =_xlfn.XLOOKUP(A92,'Salary Structure'!A:A,'Salary Structure'!C:C,"NOT FOUND")*E92/C92 -> 11612.903 | H92: =_xlfn.XLOOKUP(A92,'Salary Structure'!A:A,'Salary Structure'!D:D,"NOT FOUND")*E92/C92 -> 2903.2258 | I92: =_xlfn.XLOOKUP(A92,'Salary Structure'!A:A,'Salary Structure'!E:E,"NOT FOUND")*E92/C92 -> 4838.7097 | J92: 0 | K92: =ROUND(F92*E92/C92,0) -> 29032 | L92: =SUM(G92:K92) -> 48386.839 | M92: =F92*12/100 -> 3600 | N92: =L92*75/10000 -> 362.90129 | O92: 208 | P92: =L92*3/100 -> 1451.6052 | Q92: 0 | S92: =M92+N92+O92+P92+Q92 -> 5622.5065 | T92: =L92-S92 -> 42764.332
A93: EMP002 | B93: 46296 | C93: =DAY(EOMONTH(B93,0)) -> 31 | D93: 4 | E93: =C93-D93 -> 27 | F93: =_xlfn.XLOOKUP(A93,'Salary Structure'!A:A,'Salary Structure'!B:B,"NOT FOUND") -> 25000 | G93: =_xlfn.XLOOKUP(A93,'Salary Structure'!A:A,'Salary Structure'!C:C,"NOT FOUND")*E93/C93 -> 8709.6774 | H93: =_xlfn.XLOOKUP(A93,'Salary Structure'!A:A,'Salary Structure'!D:D,"NOT FOUND")*E93/C93 -> 2177.4194 | I93: =_xlfn.XLOOKUP(A93,'Salary Structure'!A:A,'Salary Structure'!E:E,"NOT FOUND")*E93/C93 -> 3483.871 | J93: 0 | K93: =ROUND(F93*E93/C93,0) -> 21774 | L93: =SUM(G93:K93) -> 36144.968 | M93: =F93*12/100 -> 3000 | N93: =L93*75/10000 -> 271.08726 | O93: 208 | P93: =L93*3/100 -> 1084.349 | Q93: 0 | S93: =M93+N93+O93+P93+Q93 -> 4563.4363 | T93: =L93-S93 -> 31581.531
A94: EMP003 | B94: 46296 | C94: =DAY(EOMONTH(B94,0)) -> 31 | D94: 0 | E94: =C94-D94 -> 31 | F94: =_xlfn.XLOOKUP(A94,'Salary Structure'!A:A,'Salary Structure'!B:B,"NOT FOUND") -> 28000 | G94: =_xlfn.XLOOKUP(A94,'Salary Structure'!A:A,'Salary Structure'!C:C,"NOT FOUND")*E94/C94 -> 11200 | H94: =_xlfn.XLOOKUP(A94,'Salary Structure'!A:A,'Salary Structure'!D:D,"NOT FOUND")*E94/C94 -> 2800 | I94: =_xlfn.XLOOKUP(A94,'Salary Structure'!A:A,'Salary Structure'!E:E,"NOT FOUND")*E94/C94 -> 4500 | J94: 0 | K94: =ROUND(F94*E94/C94,0) -> 28000 | L94: =SUM(G94:K94) -> 46500 | M94: =F94*12/100 -> 3360 | N94: =L94*75/10000 -> 348.75 | O94: 208 | P94: =L94*3/100 -> 1395 | Q94: 300 | R94: Loan/Advance EMI recovery | S94: =M94+N94+O94+P94+Q94 -> 5611.75 | T94: =L94-S94 -> 40888.25
A95: EMP004 | B95: 46296 | C95: =DAY(EOMONTH(B95,0)) -> 31 | D95: 2 | E95: =C95-D95 -> 29 | F95: =_xlfn.XLOOKUP(A95,'Salary Structure'!A:A,'Salary Structure'!B:B,"NOT FOUND") -> 26000 | G95: =_xlfn.XLOOKUP(A95,'Salary Structure'!A:A,'Salary Structure'!C:C,"NOT FOUND")*E95/C95 -> 9729.0323 | H95: =_xlfn.XLOOKUP(A95,'Salary Structure'!A:A,'Salary Structure'!D:D,"NOT FOUND")*E95/C95 -> 2432.2581 | I95: =_xlfn.XLOOKUP(A95,'Salary Structure'!A:A,'Salary Structure'!E:E,"NOT FOUND")*E95/C95 -> 3741.9355 | J95: 0 | K95: =ROUND(F95*E95/C95,0) -> 24323 | L95: =SUM(G95:K95) -> 40226.226 | M95: =F95*12/100 -> 3120 | N95: =L95*75/10000 -> 301.69669 | O95: 208 | P95: =L95*3/100 -> 1206.7868 | Q95: 0 | S95: =M95+N95+O95+P95+Q95 -> 4836.4835 | T95: =L95-S95 -> 35389.742
A96: EMP005 | B96: 46296 | C96: =DAY(EOMONTH(B96,0)) -> 31 | D96: 0 | E96: =C96-D96 -> 31 | F96: =_xlfn.XLOOKUP(A96,'Salary Structure'!A:A,'Salary Structure'!B:B,"NOT FOUND") -> 32000 | G96: =_xlfn.XLOOKUP(A96,'Salary Structure'!A:A,'Salary Structure'!C:C,"NOT FOUND")*E96/C96 -> 12800 | H96: =_xlfn.XLOOKUP(A96,'Salary Structure'!A:A,'Salary Structure'!D:D,"NOT FOUND")*E96/C96 -> 3200 | I96: =_xlfn.XLOOKUP(A96,'Salary Structure'!A:A,'Salary Structure'!E:E,"NOT FOUND")*E96/C96 -> 5500 | J96: 0 | K96: =ROUND(F96*E96/C96,0) -> 32000 | L96: =SUM(G96:K96) -> 53500 | M96: =F96*12/100 -> 3840 | N96: =L96*75/10000 -> 401.25 | O96: 208 | P96: =L96*3/100 -> 1605 | Q96: 0 | S96: =M96+N96+O96+P96+Q96 -> 6054.25 | T96: =L96-S96 -> 47445.75
A97: EMP006 | B97: 46296 | C97: =DAY(EOMONTH(B97,0)) -> 31 | D97: 4 | E97: =C97-D97 -> 27 | F97: =_xlfn.XLOOKUP(A97,'Salary Structure'!A:A,'Salary Structure'!B:B,"NOT FOUND") -> 24000 | G97: =_xlfn.XLOOKUP(A97,'Salary Structure'!A:A,'Salary Structure'!C:C,"NOT FOUND")*E97/C97 -> 8361.2903 | H97: =_xlfn.XLOOKUP(A97,'Salary Structure'!A:A,'Salary Structure'!D:D,"NOT FOUND")*E97/C97 -> 2090.3226 | I97: =_xlfn.XLOOKUP(A97,'Salary Structure'!A:A,'Salary Structure'!E:E,"NOT FOUND")*E97/C97 -> 3048.3871 | J97: 0 | K97: =ROUND(F97*E97/C97,0) -> 20903 | L97: =SUM(G97:K97) -> 34403 | M97: =F97*12/100 -> 2880 | N97: =L97*75/10000 -> 258.0225 | O97: 208 | P97: =L97*3/100 -> 1032.09 | Q97: 0 | S97: =M97+N97+O97+P97+Q97 -> 4378.1125 | T97: =L97-S97 -> 30024.888
A98: EMP007 | B98: 46296 | C98: =DAY(EOMONTH(B98,0)) -> 31 | D98: 1 | E98: =C98-D98 -> 30 | F98: =_xlfn.XLOOKUP(A98,'Salary Structure'!A:A,'Salary Structure'!B:B,"NOT FOUND") -> 40000 | G98: =_xlfn.XLOOKUP(A98,'Salary Structure'!A:A,'Salary Structure'!C:C,"NOT FOUND")*E98/C98 -> 15483.871 | H98: =_xlfn.XLOOKUP(A98,'Salary Structure'!A:A,'Salary Structure'!D:D,"NOT FOUND")*E98/C98 -> 3870.9677 | I98: =_xlfn.XLOOKUP(A98,'Salary Structure'!A:A,'Salary Structure'!E:E,"NOT FOUND")*E98/C98 -> 6774.1935 | J98: 0 | K98: =ROUND(F98*E98/C98,0) -> 38710 | L98: =SUM(G98:K98) -> 64839.032 | M98: =F98*12/100 -> 4800 | N98: =L98*75/10000 -> 486.29274 | O98: 208 | P98: =L98*3/100 -> 1945.171 | Q98: 0 | S98: =M98+N98+O98+P98+Q98 -> 7439.4637 | T98: =L98-S98 -> 57399.569
A99: EMP008 | B99: 46296 | C99: =DAY(EOMONTH(B99,0)) -> 31 | D99: 4 | E99: =C99-D99 -> 27 | F99: =_xlfn.XLOOKUP(A99,'Salary Structure'!A:A,'Salary Structure'!B:B,"NOT FOUND") -> 30000 | G99: =_xlfn.XLOOKUP(A99,'Salary Structure'!A:A,'Salary Structure'!C:C,"NOT FOUND")*E99/C99 -> 10451.613 | H99: =_xlfn.XLOOKUP(A99,'Salary Structure'!A:A,'Salary Structure'!D:D,"NOT FOUND")*E99/C99 -> 2612.9032 | I99: =_xlfn.XLOOKUP(A99,'Salary Structure'!A:A,'Salary Structure'!E:E,"NOT FOUND")*E99/C99 -> 4354.8387 | J99: 0 | K99: =ROUND(F99*E99/C99,0) -> 26129 | L99: =SUM(G99:K99) -> 43548.355 | M99: =F99*12/100 -> 3600 | N99: =L99*75/10000 -> 326.61266 | O99: 208 | P99: =L99*3/100 -> 1306.4506 | Q99: 0 | S99: =M99+N99+O99+P99+Q99 -> 5441.0633 | T99: =L99-S99 -> 38107.292
A100: EMP009 | B100: 46296 | C100: =DAY(EOMONTH(B100,0)) -> 31 | D100: 0 | E100: =C100-D100 -> 31 | F100: =_xlfn.XLOOKUP(A100,'Salary Structure'!A:A,'Salary Structure'!B:B,"NOT FOUND") -> 23000 | G100: =_xlfn.XLOOKUP(A100,'Salary Structure'!A:A,'Salary Structure'!C:C,"NOT FOUND")*E100/C100 -> 9200 | H100: =_xlfn.XLOOKUP(A100,'Salary Structure'!A:A,'Salary Structure'!D:D,"NOT FOUND")*E100/C100 -> 2300 | I100: =_xlfn.XLOOKUP(A100,'Salary Structure'!A:A,'Salary Structure'!E:E,"NOT FOUND")*E100/C100 -> 3500 | J100: 0 | K100: =ROUND(F100*E100/C100,0) -> 23000 | L100: =SUM(G100:K100) -> 38000 | M100: =F100*12/100 -> 2760 | N100: =L100*75/10000 -> 285 | O100: 208 | P100: =L100*3/100 -> 1140 | Q100: 0 | S100: =M100+N100+O100+P100+Q100 -> 4393 | T100: =L100-S100 -> 33607
...

Sheet Salary Slip
A1: Stark Industries
A3: Indore, Madhya Pradesh | hr@stark.example | +91 90231 10213
A5: SALARY SLIP
A7: Employee ID | B7: EMP005 | F7: Salary Month | G7: 46266
A11: EMPLOYEE DETAILS | F11: ATTENDANCE
A12: Employee Name | C12: =_xlfn.XLOOKUP('Salary Slip'!B7,'Employee Master Table'!A:A,'Employee Master Table'!B:B,"NOTFOUND") -> Rahul Mehta | F12: Salary Month | H12: {=VLOOKUP($B$7,_xlfn._xlws.FILTER('Employee data'!$A$1:$T$121,'Employee data'!$B$1:$B$121='Salary Slip'!$G$7),MATCH(F12,'Employee data'!$1:$1,0),0)} -> 46266
A13: Department | C13: =_xlfn.XLOOKUP('Salary Slip'!B7,'Employee Master Table'!A:A,'Employee Master Table'!D:D,"NOTFOUND") -> Engineering | F13: Working Days | H13: {=VLOOKUP($B$7,_xlfn._xlws.FILTER('Employee data'!$A$1:$T$121,'Employee data'!$B$1:$B$121='Salary Slip'!$G$7),MATCH(F13,'Employee data'!$1:$1,0),0)} -> 30
A14: Designation | C14: =_xlfn.XLOOKUP('Salary Slip'!B7,'Employee Master Table'!A:A,'Employee Master Table'!E:E,"NOTFOUND") -> Data Analyst | F14: LOP Days | H14: {=VLOOKUP($B$7,_xlfn._xlws.FILTER('Employee data'!$A$1:$T$121,'Employee data'!$B$1:$B$121='Salary Slip'!$G$7),MATCH(F14,'Employee data'!$1:$1,0),0)} -> 4
A15: Date of Joining | C15: =_xlfn.XLOOKUP('Salary Slip'!B7,'Employee Master Table'!A:A,'Employee Master Table'!F:F,"NOTFOUND") -> 45516 | F15: Paid Days | H15: {=VLOOKUP($B$7,_xlfn._xlws.FILTER('Employee data'!$A$1:$T$121,'Employee data'!$B$1:$B$121='Salary Slip'!$G$7),MATCH(F15,'Employee data'!$1:$1,0),0)} -> 26
A16: Bank Name | C16: =_xlfn.XLOOKUP('Salary Slip'!B7,'Employee Master Table'!A:A,'Employee Master Table'!G:G,"NOTFOUND") -> HDFC Bank
A17: Bank Account No. | C17: =LEFT(_xlfn.XLOOKUP('Salary Slip'!B7,'Employee Master Table'!A:A,'Employee Master Table'!H:H,"NOTFOUND"),3)&"********"&RIGHT(_xlfn.XLOOKUP('Salary Slip'!B7,'Employee Master Table'!A:A,'Employee Master Table'!H:H,"NOTFOUND"),3) -> 501********005
A18: PAN | C18: =LEFT(_xlfn.XLOOKUP('Salary Slip'!B7,'Employee Master Table'!A:A,'Employee Master Table'!I:I,"NOTFOUND"),2)&"******"&RIGHT(_xlfn.XLOOKUP('Salary Slip'!B7,'Employee Master Table'!A:A,'Employee Master Table'!I:I,"NOTFOUND"),2) -> EE******8E
A19: Status | C19: =_xlfn.XLOOKUP('Salary Slip'!B7,'Employee Master Table'!A:A,'Employee Master Table'!L:L,"NOTFOUND") -> Active
A21: EARNINGS | F21: DEDUCTIONS
A22: Basic Salary | D22: {=VLOOKUP($B$7,_xlfn._xlws.FILTER('Employee data'!$A$1:$T$121,'Employee data'!$B$1:$B$121='Salary Slip'!$G$7),MATCH(A22,'Employee data'!$1:$1,0),0)} -> 32000 | F22: Provident Fund (PF) | H22: {=VLOOKUP($B$7,_xlfn._xlws.FILTER('Employee data'!$A$1:$T$121,'Employee data'!$B$1:$B$121='Salary Slip'!$G$7),MATCH(F22,'Employee data'!$1:$1,0),0)} -> 3840
A23: House Rent Allowance | D23: {=VLOOKUP($B$7,_xlfn._xlws.FILTER('Employee data'!$A$1:$T$121,'Employee data'!$B$1:$B$121='Salary Slip'!$G$7),MATCH(A23,'Employee data'!$1:$1,0),0)} -> 11093.333 | F23: ESI | H23: {=VLOOKUP($B$7,_xlfn._xlws.FILTER('Employee data'!$A$1:$T$121,'Employee data'!$B$1:$B$121='Salary Slip'!$G$7),MATCH(F23,'Employee data'!$1:$1,0),0)} -> 347.7475
A24: Conveyance Allowance | D24: {=VLOOKUP($B$7,_xlfn._xlws.FILTER('Employee data'!$A$1:$T$121,'Employee data'!$B$1:$B$121='Salary Slip'!$G$7),MATCH(A24,'Employee data'!$1:$1,0),0)} -> 2773.3333 | F24: Professional Tax | H24: {=VLOOKUP($B$7,_xlfn._xlws.FILTER('Employee data'!$A$1:$T$121,'Employee data'!$B$1:$B$121='Salary Slip'!$G$7),MATCH(F24,'Employee data'!$1:$1,0),0)} -> 208
A25: Special Allowance | D25: {=VLOOKUP($B$7,_xlfn._xlws.FILTER('Employee data'!$A$1:$T$121,'Employee data'!$B$1:$B$121='Salary Slip'!$G$7),MATCH(A25,'Employee data'!$1:$1,0),0)} -> 4766.6667 | F25: TDS | H25: {=VLOOKUP($B$7,_xlfn._xlws.FILTER('Employee data'!$A$1:$T$121,'Employee data'!$B$1:$B$121='Salary Slip'!$G$7),MATCH(F25,'Employee data'!$1:$1,0),0)} -> 1390.99
A26: Other Earnings | D26: {=VLOOKUP($B$7,_xlfn._xlws.FILTER('Employee data'!$A$1:$T$121,'Employee data'!$B$1:$B$121='Salary Slip'!$G$7),MATCH(A26,'Employee data'!$1:$1,0),0)} -> 0 | F26: Other Deductions | H26: {=VLOOKUP($B$7,_xlfn._xlws.FILTER('Employee data'!$A$1:$T$121,'Employee data'!$B$1:$B$121='Salary Slip'!$G$7),MATCH(F26,'Employee data'!$1:$1,0),0)} -> 0
A27: GROSS EARNINGS | D27: {=VLOOKUP($B$7,_xlfn._xlws.FILTER('Employee data'!$A$1:$T$121,'Employee data'!$B$1:$B$121='Salary Slip'!$G$7),MATCH(A27,'Employee data'!$1:$1,0),0)} -> 46366.333 | F27: TOTAL DEDUCTIONS | H27: {=VLOOKUP($B$7,_xlfn._xlws.FILTER('Employee data'!$A$1:$T$121,'Employee data'!$B$1:$B$121='Salary Slip'!$G$7),MATCH(F27,'Employee data'!$1:$1,0),0)} -> 5786.7375
A29: NET SALARY PAYABLE | F29: {=VLOOKUP($B$7,_xlfn._xlws.FILTER('Employee data'!$A$1:$T$121,'Employee data'!$B$1:$B$121='Salary Slip'!$G$7),20,0)} -> 40579.596
A30: =LEFT(_xlfn.XLOOKUP(B7,'Employee Master Table'!A:A,'Employee Master Table'!C:C), FIND(" ", _xlfn.XLOOKUP(B7,'Employee Master Table'!A:A,'Employee Master Table'!C:C)) - 1) -> Rahul | F30: Vishwas
A32: Employee Signatory | F32: Authorized Signatory
F33: Stark Industries
